Workbook

Sheet Drivers & Assumptons
A1: Category | B1: Item | C1: Value | D1: Notes / Units
A2: Model Timeline | B2: Model Start Year | C2: 2022 | D2: First year in model
A3: Model Timeline | B3: Model Start Date | C3: 44592 | D3: For monthly builds
A4: Model Timeline | B4: Forecast End Year | C4: 2032 | D4: Last year in projection
A5: USDC Metrics | B5: USDC Circulation Growth (Base) | C5: 0.08 | D5: YoY growth rate assumption: Historical growth: 2022 = 5.04%, 2023 = –44.69%, 2024 = 77.98%, 2025 (annualized) = 95.57%. Base case assumes normalized adoption rate between historical median (5%) and trimmed recovery (~37%).
A6: USDC Metrics | B6: Avg Float % of Circulation | C6: 1 | D6: Portion of circulation invested in reserves - Based on 3-year historical average (2022–2024) of 100.5%.
A7: USDC Metrics | B7: Daily Weighted-Average % of USDC on Platform | C7: -
A8: USDC Metrics | B8: Revenue Sharing Rate (on off platform USDC) | C8: -
A9: Circle Metrics | B9: Circle Platform % of Circulation | C9: 0.08
A10: Coinbase Metrics | B10: Coinbase Platform % of Circulation | C10: 0.24
A11: Outside Rate | B11: Outside Platforms % of Circulation | C11: 0.7
A12: Coinbase Metrics | B12: Coinbase Retained % | C12: 1
A13: Other Platorms | B13: Other Platforms Retained % | C13: 1
A14: Reserve Yields | B14: 3M T-Bill Yield (Base) | C14: 0.0497 | D14: Used for Treasuries portion - Average of Circle provided quarterly rates
A15: Reserve Yields | B15: SOFR Rate (Base) | C15: 0.0515 | D15: Used for repo portion - Average of Circle provided quarterly rates
A16: Reserve Yields | B16: Cash Yield (Base) | C16: 0.10% | D16: Used for cash portion
A17: Rates | B17: Forecasted Weighted Yield Rate | C17: 0.041 | D17: Short-term rates will gradually decline in H2 2025 (based on macro expectations for rate cuts) - within the 3.75 - 3.97% range
A18: Rates | B18: Effective Tax Rate | C18: 0.21 | D18: Based on FY2024 effective tax rate per Circle disclosure; 2025 rate excluded due to IPO-related discrete items. 35% historical rate -> phased down to avoid understating profitability
A19: Transaction Assumptions | B19: Transaction Volume Growth (Base) | C19: 0.12 | D19: YoY growth - Base set via weighted geometric mean of YoY factors: 2023 (w=0.20), 2024 (w=0.40), 2025 annualized (w=0.40). Result ≈ 11.24%; rounded to 12%. 2025 uses H1×2.
A20: Transaction Assumptions | B20: Take Rate | C20: 0.0002 | D20: % of transaction value captured as fee revenue (on/off-ramp fee take rate)
A21: Expense Drivers | B21: Partner Payout Rate (on Reserve Income) | C21: 0.5 | D21: Paid to partners from float income
A22: Expense Drivers | B22: Cost of Revenue % of Total Revenue | C22: 0.61019 | D22: Payment processing & network costs
A23: Expense Drivers | B23: Compensation Expense % of Total Revenue | C23: 0.19065 | D23: Compensation Expenses - Internal costs
A24: Expense Drivers | B24: Sales & Marketing % of Revenue | C24: 0.01 | D24: Opex driver
A25: Expense Drivers | B25: R&D % of Total Revenue | C25: 0.015 | D25: Opex driver
A26: Expense Drivers | B26: G&A % of Total Revenue | C26: 0.06 | D26: Opex driver
A27: Expense Drivers | B27: D&A % of Total Revenue | C27: 0.0226 | D27: Opex driver
A28: Expense Drivers | B28: IT & Infrastructure % Total Revenue | C28: 0.01329 | D28: Opex driver
... A31: Scenario Toggles | B31: Take Rate Delta (%) | C31: 0 | D31: Adjusts transaction fees
A33: Cash & CE | B33: Corporate Supply | C33: 0.15
A34: Cash & CE | B34: USDC for holders | C34: 0.08
A35: DSO | B35: AR % of Total Revenue | C35: =AVERAGE(('Balance Sheet'!D10/'P&L'!E2),('Balance Sheet'!C10/'P&L'!D2)) -> 0.0072574484
A36: AP | B36: AP % Total Costs | C36: =AVERAGE(('Balance Sheet'!B29/('Expense Build'!C6+'Expense Build'!C18)),('Balance Sheet'!C29/('Expense Build'!D6+'Expense Build'!D18)),('Balance Sheet'!D29/('Expense Build'!E6+'Expense Build'!E18))) -> 0.19983327
A37: AP | B37: AP % of Opex | C37: =AVERAGE(('Balance Sheet'!D29/'P&L'!E22),('Balance Sheet'!C29/'P&L'!D22),('Balance Sheet'!B29/'P&L'!C22)) -> 0.49872962
A38: Prepaid Exp & Other Current Exp | B38: % of Opex | C38: =AVERAGE(('Balance Sheet'!B12/'P&L'!C22),('Balance Sheet'!C12/'P&L'!D22),('Balance Sheet'!D12/'P&L'!E22)) -> 0.3359993
A39: Fixed Assets | B39: % of Opex | C39: =AVERAGE(('Balance Sheet'!D17/'P&L'!E22),('Balance Sheet'!C17/'P&L'!D22),('Balance Sheet'!B17/'P&L'!C22)) -> 0.02569238
A40: Fixed Assets 2025E | B40: Fixed Percentage assumed at 20% | C40: 0.2
A41: Other Assets/Liabilities | B41: % of Total Revenue
A42: Deferred Revenue | B42: % of Transaction Revenue | C42: =AVERAGE(('Balance Sheet'!B28/'P&L'!C2),('Balance Sheet'!C28/'P&L'!D2),('Balance Sheet'!D28/'P&L'!E2)) -> 0.0055300039
A44: Stock Compensation | B44: % of Total Compensation Expense | C44: =AVERAGE(('Cash Flow Statement'!B17/'Expense Build'!B9),('Cash Flow Statement'!C17/'Expense Build'!C9),('Cash Flow Statement'!D17/'Expense Build'!D9)) -> 0.29345754
A45: AFS Maturity Rate | B45: Average historical ratio of AFS (available-for-sale) | C45: 0.95
A46: IPO Costs | B46: Underwriting & related IPO fees | C46: 0.059
A48: Perpetuity Growth Rate | B48: Terminal Growth Rate | C48: 0.025 | D48: Believe in growth of stablecoins over GDP - Added an inflation adjustment
A49: Exit Multiple | B49: Comparable Exit Multiple Assumption | C49: 8 | D49: – Fintech & exchange comps (Coinbase, PayPal, Robinhood, etc.) usually trade in the 6×–12× forward EBITDA range depending on cycle and profitability.
D50: – Given Circle is USDC-driven, likely lower end than PayPal but maybe higher than COIN (which is very volatile). Something like 7×–9× could be reasonable.
A51: Hiring Rate | B51: Driver for Headcount Growth | C51: 0.08 | D51: 2025E = 8% tapered down to 5% by 2032E.

Sheet Revenue Build
A1: (in millions) | B1: ='Drivers & Assumptons'!C2 & "A" -> 2022A | C1: =LEFT(B1,4) + 1 & IF(LEFT(B1,4) + 1 <= 2024, "A", "E") -> 2023A | D1: =LEFT(C1,4) + 1 & IF(LEFT(C1,4) + 1 <= 2024, "A", "E") -> 2024A | E1: 2025 6M Actual | F1: =LEFT(D1,4) + 1 & IF(LEFT(D1,4) + 1 <= 2024, "A", "E") -> 2025E | G1: =LEFT(F1,4) + 1 & IF(LEFT(F1,4) + 1 <= 2024, "A", "E") -> 2026E | H1: =LEFT(G1,4) + 1 & IF(LEFT(G1,4) + 1 <= 2024, "A", "E") -> 2027E | I1: =LEFT(H1,4) + 1 & IF(LEFT(H1,4) + 1 <= 2024, "A", "E") -> 2028E | J1: =LEFT(I1,4) + 1 & IF(LEFT(I1,4) + 1 <= 2024, "A", "E") -> 2029E | K1: =LEFT(J1,4) + 1 & IF(LEFT(J1,4) + 1 <= 2024, "A", "E") -> 2030E | L1: =LEFT(K1,4) + 1 & IF(LEFT(K1,4) + 1 <= 2024, "A", "E") -> 2031E | M1: =LEFT(L1,4) + 1 & IF(LEFT(L1,4) + 1 <= 2024, "A", "E") -> 2032E
A2: USDC Circulation (Base, in millions) BOY | B2: 42416 | C2: 44554 | D2: 24412 | E2: 43857 | F2: =E2 -> 43857 | G2: =F3 -> 63739.123 | H2: =G3 -> 68838.253 | I2: =H3 -> 74345.313 | J2: =I3 -> 80292.939 | K2: =J3 -> 86716.374 | L2: =K3 -> 93653.683 | M2: =L3 -> 101145.98
A3: USDC Circulation (Base, in millions) EOY | B3: 44554 | C3: 24412 | D3: 43857 | E3: 61333 | F3: =E3*(1+'Drivers & Assumptons'!C5)^0.5 -> 63739.123 | G3: =G2*(1+'Drivers & Assumptons'!$C$5) -> 68838.253 | H3: =H2*(1+'Drivers & Assumptons'!$C$5) -> 74345.313 | I3: =I2*(1+'Drivers & Assumptons'!$C$5) -> 80292.939 | J3: =J2*(1+'Drivers & Assumptons'!$C$5) -> 86716.374 | K3: =K2*(1+'Drivers & Assumptons'!$C$5) -> 93653.683 | L3: =L2*(1+'Drivers & Assumptons'!$C$5) -> 101145.98 | M3: =M2*(1+'Drivers & Assumptons'!$C$5) -> 109237.66
A4: Growth EOY % | C4: =(C3-B3)/B3 -> -0.45208062 | D4: =(D3-C3)/C3 -> 0.79653449 | E4: =(E3-D3)/D3 -> 0.39847687 | F4: =(F3-E3)/E3 -> 0.039230485 | G4: =(G3-F3)/F3 -> 0.08 | H4: =(H3-G3)/G3 -> 0.08 | I4: =(I3-H3)/H3 -> 0.08 | J4: =(J3-I3)/I3 -> 0.08 | ... M4: =(M3-L3)/L3 -> 0.08
A5: USDC Circulation (Base, in millions) Average | B5: 49861 | C5: 30467 | D5: 33342 | E5: 57574 | F5: =((E5*6)+((((E3+F3)/2)*6))) / 12 -> 60055.031 | G5: =(G2+G3)/2 -> 66288.688 | H5: =(H2+H3)/2 -> 71591.783 | I5: =(I2+I3)/2 -> 77319.126 | J5: =(J2+J3)/2 -> 83504.656 | K5: =(K2+K3)/2 -> 90185.029 | L5: =(L2+L3)/2 -> 97399.831 | M5: =(M2+M3)/2 -> 105191.82
A6: Avg Float % of Circulation | B6: =[1]Calculations!$J$2 -> 0.99926934 | C6: =[1]Calculations!$J$3 -> 1.0208429 | D6: =[1]Calculations!$J$4 -> 0.99501889 | E6: =[1]Calculations!$J$5 -> 0.98424448 | F6: =((E6*E5)+(F5*'Drivers & Assumptons'!C6))/('Revenue Build'!E5+'Revenue Build'!F5) -> 0.9922884 | G6: =AVERAGE($B$6:$F$6) -> 0.99833281 | H6: =AVERAGE($B$6:$F$6) -> 0.99833281 | I6: =AVERAGE($B$6:$F$6) -> 0.99833281 | J6: =AVERAGE($B$6:$F$6) -> 0.99833281 | K6: =AVERAGE($B$6:$F$6) -> 0.99833281 | L6: =AVERAGE($B$6:$F$6) -> 0.99833281 | M6: =AVERAGE($B$6:$F$6) -> 0.99833281
A7: Implied Float % of Circulation | B7: =B21/(B5*B8) -> 0.98391528 | C7: =C21/(C5*C8) -> 0.99906212 | D7: =D21/(D5*D8) -> 0.99639134 | E7: =E21/(E5*E8) -> 0.49302388 | F7: =F21/(F5*F8) -> 0.97361981 | G7: =G21/(G5*G8) -> 0.99833281 | H7: =H21/(H5*H8) -> 0.99833281 | I7: =I21/(I5*I8) -> 0.99833281 | ... M7: =M21/(M5*M8) -> 0.99833281
A8: Reserve Return Rate | B8: 0.015 | C8: 0.047 | D8: 0.05 | E8: 0.042 | F8: =((E8*6)+('Drivers & Assumptons'!C17*6))/12 -> 0.0415 | G8: =[1]Metrics!$D$9 -> 0.033 | H8: =[1]Metrics!$D$10 -> 0.0295 | I8: =[1]Metrics!$D$11 -> 0.0275 | J8: =[1]Metrics!$D$12 -> 0.0255 | K8: =[1]Metrics!$D$13 -> 0.025 | L8: =[1]Metrics!$D$14 -> 0.025 | M8: =[1]Metrics!$D$15 -> 0.026
A9: Base Gross Reserve Income (Circle Retains 100%) | B9: =B5*B7*B8 -> 735.885 | C9: =C5*C7*C8 -> 1430.606 | D9: =D5*D7*D8 -> 1661.084 | E9: =E5*E7*E8 -> 1192.185 | F9: =F5*F7*F8 -> 2426.5369 | G9: =G5*G7*G8 -> 2183.8797 | H9: =H5*H7*H8 -> 2108.4366 | I9: =I5*I7*I8 -> 2122.731 | ... M9: =M5*M7*M8 -> 2730.4275
A10: Circle % of Float | B10: 0.01 | C10: 0.02 | D10: 0.05 | E10: 0.07 | F10: ='Drivers & Assumptons'!C9 -> 0.08 | G10: =F10+0.01 -> 0.09 | H10: =G10+0.01 -> 0.1 | I10: =H10+0.01 -> 0.11 | J10: =I10+0.01 -> 0.12 | K10: =J10+0.01 -> 0.13 | L10: =K10+0.01 -> 0.14 | M10: =L10+0.01 -> 0.15
A11: Circle Gross Reserve Income | B11: =B9*B10 -> 7.35885 | C11: =C9*C10 -> 28.61212 | D11: =D9*D10 -> 83.0542 | E11: =E9*E10 -> 83.45295 | F11: =F9*F10 -> 194.12295 | G11: =G9*G10 -> 196.54917 | H11: =H9*H10 -> 210.84366 | I11: =I9*I10 -> 233.50042 | ... M11: =M9*M10 -> 409.56412
A12: Coinbase % of Float | B12: 0.05 | C12: 0.12 | D12: 0.2 | E12: 0.23 | F12: ='Drivers & Assumptons'!C10 -> 0.24 | G12: =F12+0.01 -> 0.25 | H12: =G12 -> 0.25 | I12: =H12 -> 0.25 | J12: =I12+0.01 -> 0.26 | K12: =J12 -> 0.26 | L12: =K12 -> 0.26 | M12: =L12+0.01 -> 0.27
A13: Coinbase Gross Reserve Income | B13: =B9*B12 -> 36.79425 | C13: =C9*C12 -> 171.67272 | D13: =D9*D12 -> 332.2168 | E13: =E9*E12 -> 274.20255 | F13: =F9*F12 -> 582.36885 | G13: =G9*G12 -> 545.96992 | H13: =H9*H12 -> 527.10914 | I13: =I9*I12 -> 530.68276 | ... M13: =M9*M12 -> 737.21542
A14: Coinbase Retained % | B14: ='Drivers & Assumptons'!$C$12 -> 1 | C14: ='Drivers & Assumptons'!$C$12 -> 1 | D14: ='Drivers & Assumptons'!$C$12 -> 1 | E14: ='Drivers & Assumptons'!$C$12 -> 1 | F14: ='Drivers & Assumptons'!$C$12 -> 1 | G14: ='Drivers & Assumptons'!$C$12 -> 1 | H14: ='Drivers & Assumptons'!$C$12 -> 1 | I14: ='Drivers & Assumptons'!$C$12 -> 1 | ... M14: ='Drivers & Assumptons'!$C$12 -> 1
A15: Coinbase Net Reserve Income | B15: =B13*B14 -> 36.79425 | C15: =C13*C14 -> 171.67272 | D15: =D13*D14 -> 332.2168 | E15: =E13*E14 -> 274.20255 | F15: =F13*F14 -> 582.36885 | G15: =G13*G14 -> 545.96992 | H15: =H13*H14 -> 527.10914 | I15: =I13*I14 -> 530.68276 | ... M15: =M13*M14 -> 737.21542
A16: Outside % of Float | B16: 0.94 | C16: 0.86 | D16: 0.75 | E16: 0.7 | F16: =1-F10-F12 -> 0.68 | G16: =1-G10-G12 -> 0.66 | H16: =1-H10-H12 -> 0.65 | I16: =1-I10-I12 -> 0.64 | J16: =1-J10-J12 -> 0.62 | K16: =1-K10-K12 -> 0.61 | L16: =1-L10-L12 -> 0.6 | M16: =1-M10-M12 -> 0.58
A17: Outside Gross Reserve Income | B17: =B9*B16 -> 691.7319 | C17: =C9*C16 -> 1230.3212 | D17: =D9*D16 -> 1245.813 | E17: =E9*E16 -> 834.5295 | F17: =F9*F16 -> 1650.0451 | G17: =G9*G16 -> 1441.3606 | H17: =H9*H16 -> 1370.4838 | I17: =I9*I16 -> 1358.5479 | ... M17: =M9*M16 -> 1583.6479
A18: Outside Retained % | B18: ='Drivers & Assumptons'!$C$13 -> 1 | C18: ='Drivers & Assumptons'!$C$13 -> 1 | D18: ='Drivers & Assumptons'!$C$13 -> 1 | E18: ='Drivers & Assumptons'!$C$13 -> 1 | F18: ='Drivers & Assumptons'!$C$13 -> 1 | G18: ='Drivers & Assumptons'!$C$13 -> 1 | H18: ='Drivers & Assumptons'!$C$13 -> 1 | I18: ='Drivers & Assumptons'!$C$13 -> 1 | ... M18: ='Drivers & Assumptons'!$C$13 -> 1
A19: Outside Net Reserve Income | B19: =B17*B18 -> 691.7319 | C19: =C17*C18 -> 1230.3212 | D19: =D17*D18 -> 1245.813 | E19: =E17*E18 -> 834.5295 | F19: =F17*F18 -> 1650.0451 | G19: =G17*G18 -> 1441.3606 | H19: =H17*H18 -> 1370.4838 | I19: =I17*I18 -> 1358.5479 | ... M19: =M17*M18 -> 1583.6479
A20: Implied Total Reserve Income | B20: =B15+B19+B11 -> 735.885 | C20: =C15+C19+C11 -> 1430.606 | D20: =D15+D19+D11 -> 1661.084 | E20: =E15+E19+E11 -> 1192.185 | F20: =F15+F19+F11 -> 2426.5369 | G20: =G15+G19+G11 -> 2183.8797 | H20: =H15+H19+H11 -> 2108.4366 | I20: =I15+I19+I11 -> 2122.731 | ... M20: =M15+M19+M11 -> 2730.4275
A21: Total Reserve Income | B21: =735885 / 1000 -> 735.885 | C21: =1430606/1000 -> 1430.606 | D21: =1661084/1000 -> 1661.084 | E21: =1192185/1000 -> 1192.185 | F21: =((E5*E6*E8)*(6/12)) + ((F5*F6*F8)*(6/12)) -> 2426.5369 | G21: =G5*G6*G8 -> 2183.8797 | H21: =H5*H6*H8 -> 2108.4366 | I21: =I5*I6*I8 -> 2122.731 | J21: =J5*J6*J8 -> 2125.8187 | K21: =K5*K6*K8 -> 2250.8668 | L21: =L5*L6*L8 -> 2430.9362 | M21: =M5*M6*M8 -> 2730.4275
A22: Total Reserve Income Check | B22: =B20-B21 -> 0 | C22: =C20-C21 -> 0 | D22: =D20-D21 -> 0 | E22: =E20-E21 -> 0 | F22: =F20-F21 -> 0 | G22: =G20-G21 -> 0 | H22: =H20-H21 -> 0 | I22: =I20-I21 -> 0 | ... M22: =M20-M21 -> 0
A24: Transaction Volume (in millions) | B24: =[1]Metrics!$B$20 -> 333080 | C24: =[1]Metrics!$B$21 -> 211808 | D24: =[1]Metrics!$B$23 -> 263239 | E24: =[1]Metrics!$B$24 -> 173316 | F24: =[1]Metrics!$B$26 -> 346632 | G24: =F24*(1+'Drivers & Assumptons'!$C$19) -> 388227.84 | H24: =G24*(1+'Drivers & Assumptons'!$C$19) -> 434815.18 | I24: =H24*(1+'Drivers & Assumptons'!$C$19) -> 486993 | J24: =I24*(1+'Drivers & Assumptons'!$C$19) -> 545432.16 | K24: =J24*(1+'Drivers & Assumptons'!$C$19) -> 610884.02 | L24: =K24*(1+'Drivers & Assumptons'!$C$19) -> 684190.11 | M24: =L24*(1+'Drivers & Assumptons'!$C$19) -> 766292.92
A25: Take Rate | B25: =B26/B24 -> 0.00010858352 | C25: =C26/C24 -> 9.3764164e-05 | D25: =D26/D24 -> 5.762444e-05 | E25: =E26/E24 -> 0.00025656027 | F25: ='Drivers & Assumptons'!$C$20 -> 0.0002 | G25: ='Drivers & Assumptons'!$C$20 -> 0.0002 | H25: ='Drivers & Assumptons'!$C$20 -> 0.0002 | I25: ='Drivers & Assumptons'!$C$20 -> 0.0002 | J25: ='Drivers & Assumptons'!$C$20 -> 0.0002 | K25: ='Drivers & Assumptons'!$C$20 -> 0.0002 | L25: ='Drivers & Assumptons'!$C$20 -> 0.0002 | M25: ='Drivers & Assumptons'!$C$20 -> 0.0002
A26: Transaction & Other Revenue | B26: =36167 / 1000 -> 36.167 | C26: =19860/1000 -> 19.86 | D26: =15169/1000 -> 15.169 | E26: =44466/1000 -> 44.466 | F26: =F25*F24 -> 69.3264 | G26: =G25*G24 -> 77.645568 | H26: =H25*H24 -> 86.963036 | I26: =I25*I24 -> 97.3986 | J26: =J25*J24 -> 109.08643 | K26: =K25*K24 -> 122.1768 | L26: =L25*L24 -> 136.83802 | M26: =M25*M24 -> 153.25858
A28: Implied Total Revenue | B28: =B26+B21 -> 772.052 | C28: =C26+C21 -> 1450.466 | D28: =D26+D21 -> 1676.253 | E28: =E26+E21 -> 1236.651 | F28: =F26+F20 -> 2495.8633 | G28: =G20+G26 -> 2261.5252 | H28: =H20+H26 -> 2195.3996 | I28: =I20+I26 -> 2220.1296 | J28: =J20+J26 -> 2234.9051 | K28: =K20+K26 -> 2373.0436 | L28: =L20+L26 -> 2567.7742 | M28: =M20+M26 -> 2883.6861
A29: Total Revenue | B29: =772052/1000 -> 772.052 | C29: =1450466/1000 -> 1450.466 | D29: =1676253/1000 -> 1676.253 | E29: =1236651/1000 -> 1236.651 | F29: =F26+F21 -> 2495.8633 | G29: =G21+G26 -> 2261.5252 | H29: =H21+H26 -> 2195.3996 | I29: =I21+I26 -> 2220.1296 | J29: =J21+J26 -> 2234.9051 | K29: =K21+K26 -> 2373.0436 | L29: =L21+L26 -> 2567.7742 | M29: =M21+M26 -> 2883.6861

Sheet Expense Build
A1: (in millions) | B1: ='Drivers & Assumptons'!C2 & "A" -> 2022A | C1: =LEFT(B1,4) + 1 & IF(LEFT(B1,4) + 1 <= 2024, "A", "E") -> 2023A | D1: =LEFT(C1,4) + 1 & IF(LEFT(C1,4) + 1 <= 2024, "A", "E") -> 2024A | E1: 2025 6M Actual | F1: =LEFT(D1,4) + 1 & IF(LEFT(D1,4) + 1 <= 2024, "A", "E") -> 2025E | G1: =LEFT(F1,4) + 1 & IF(LEFT(F1,4) + 1 <= 2024, "A", "E") -> 2026E | H1: =LEFT(G1,4) + 1 & IF(LEFT(G1,4) + 1 <= 2024, "A", "E") -> 2027E | I1: =LEFT(H1,4) + 1 & IF(LEFT(H1,4) + 1 <= 2024, "A", "E") -> 2028E | J1: =LEFT(I1,4) + 1 & IF(LEFT(I1,4) + 1 <= 2024, "A", "E") -> 2029E | K1: =LEFT(J1,4) + 1 & IF(LEFT(J1,4) + 1 <= 2024, "A", "E") -> 2030E | L1: =LEFT(K1,4) + 1 & IF(LEFT(K1,4) + 1 <= 2024, "A", "E") -> 2031E | M1: =LEFT(L1,4) + 1 & IF(LEFT(L1,4) + 1 <= 2024, "A", "E") -> 2032E
A2: Total Revenue | B2: ='Revenue Build'!B29 -> 772.052 | C2: ='Revenue Build'!C29 -> 1450.466 | D2: ='Revenue Build'!D29 -> 1676.253 | E2: ='Revenue Build'!E29 -> 1236.651 | F2: ='Revenue Build'!F29 -> 2495.8633 | G2: ='Revenue Build'!G29 -> 2261.5252 | H2: ='Revenue Build'!H29 -> 2195.3996 | I2: ='Revenue Build'!I29 -> 2220.1296 | ... M2: ='Revenue Build'!M29 -> 2883.6861
A3: Distribution & Transaction Costs | B3: =286953/1000 -> 286.953 | C3: =719806/1000 -> 719.806 | D3: =1010811/1000 -> 1010.811 | E3: =753784/1000 -> 753.784 | F3: =F2*(E3/E2) -> 1521.3199 | G3: =G2*(F3/F2) -> 1378.4823 | H3: =H2*(G3/G2) -> 1338.1763 | I3: =I2*(H3/H2) -> 1353.2502 | J3: =J2*(I3/I2) -> 1362.2564 | K3: =K2*(J3/J2) -> 1446.4568 | L3: =L2*(K3/K2) -> 1565.1522 | M3: =M2*(L3/L2) -> 1757.7121
A4: Other Costs | B4: =22401/1000 -> 22.401 | C4: =7918/1000 -> 7.918 | D4: =6553/1000 -> 6.553 | E4: =805/1000 -> 0.805 | F4: =F2*(E4/E2) -> 1.6246863 | G4: =G2*(F4/F2) -> 1.4721436 | H4: =H2*(G4/G2) -> 1.429099 | I4: =I2*(H4/H2) -> 1.445197 | J4: =J2*(I4/I2) -> 1.4548151 | K4: =K2*(J4/J2) -> 1.5447366 | L4: =L2*(K4/K2) -> 1.6714968 | M4: =M2*(L4/L2) -> 1.8771402
A5: Implied Total Distribution, Transaction, and Other Costs | B5: =B2*[1]Metrics!$D$49 -> 309.354 | C5: =C2*[1]Metrics!$D$50 -> 727.724 | D5: =D2*[1]Metrics!$D$51 -> 1017.364 | E5: =E2*[1]Metrics!$D$52 -> 754.589 | F5: =F2*'Drivers & Assumptons'!$C$22 -> 1522.9508 | G5: =G2*'Drivers & Assumptons'!$C$22 -> 1379.9601 | H5: =H2*'Drivers & Assumptons'!$C$22 -> 1339.6109 | I5: =I2*'Drivers & Assumptons'!$C$22 -> 1354.7009 | J5: =J2*'Drivers & Assumptons'!$C$22 -> 1363.7167 | K5: =K2*'Drivers & Assumptons'!$C$22 -> 1448.0075 | L5: =L2*'Drivers & Assumptons'!$C$22 -> 1566.8301 | M5: =M2*'Drivers & Assumptons'!$C$22 -> 1759.5964
A6: Total Distribution, Transaction, and Other Costs | B6: =SUM(B3:B4) -> 309.354 | C6: =SUM(C3:C4) -> 727.724 | D6: =SUM(D3:D4) -> 1017.364 | E6: =SUM(E3:E4) -> 754.589 | F6: =SUM(F3:F4) -> 1522.9446 | G6: =SUM(G3:G4) -> 1379.9545 | H6: =SUM(H3:H4) -> 1339.6054 | I6: =SUM(I3:I4) -> 1354.6954 | ... M6: =SUM(M3:M4) -> 1759.5892
A8: Operating Expenses
A9: Compensation Expenses | B9: =212961/1000 -> 212.961 | C9: =296055/1000 -> 296.055 | D9: =263410/1000 -> 263.41 | E9: =579012/1000 -> 579.012 | F9: =F2*'Drivers & Assumptons'!$C$23 -> 475.83633 | G9: =G2*'Drivers & Assumptons'!$C$23 -> 431.15979 | H9: =H2*'Drivers & Assumptons'!$C$23 -> 418.55293 | I9: =I2*'Drivers & Assumptons'!$C$23 -> 423.26772 | J9: =J2*'Drivers & Assumptons'!$C$23 -> 426.08466 | K9: =K2*'Drivers & Assumptons'!$C$23 -> 452.42077 | L9: =L2*'Drivers & Assumptons'!$C$23 -> 489.54615 | M9: =M2*'Drivers & Assumptons'!$C$23 -> 549.77475
A10: G & A Expenses | B10: =82272/1000 -> 82.272 | C10: =100128/1000 -> 100.128 | D10: =137283/1000 -> 137.283 | E10: =73824/1000 -> 73.824 | F10: =F2*'Drivers & Assumptons'!$C$26 -> 149.7518 | G10: =G2*'Drivers & Assumptons'!$C$26 -> 135.69151 | H10: =H2*'Drivers & Assumptons'!$C$26 -> 131.72398 | I10: =I2*'Drivers & Assumptons'!$C$26 -> 133.20778 | J10: =J2*'Drivers & Assumptons'!$C$26 -> 134.09431 | K10: =K2*'Drivers & Assumptons'!$C$26 -> 142.38262 | L10: =L2*'Drivers & Assumptons'!$C$26 -> 154.06645 | M10: =M2*'Drivers & Assumptons'!$C$26 -> 173.02116
A11: Depreciation & Amoritization Expenses | B11: =13277/1000 -> 13.277 | C11: =34887/1000 -> 34.887 | D11: =50854/1000 -> 50.854 | E11: =28089/1000 -> 28.089 | F11: =F2*'Drivers & Assumptons'!$C$27 -> 56.40651 | G11: =G2*'Drivers & Assumptons'!$C$27 -> 51.110471 | H11: =H2*'Drivers & Assumptons'!$C$27 -> 49.616031 | I11: =I2*'Drivers & Assumptons'!$C$27 -> 50.17493 | J11: =J2*'Drivers & Assumptons'!$C$27 -> 50.508855 | K11: =K2*'Drivers & Assumptons'!$C$27 -> 53.630786 | L11: =L2*'Drivers & Assumptons'!$C$27 -> 58.031696 | M11: =M2*'Drivers & Assumptons'!$C$27 -> 65.171305
A12: IT Infrastructure Costs | B12: =11835/1000 -> 11.835 | C12: =20722/1000 -> 20.722 | D12: =27109/1000 -> 27.109 | E12: =16432/1000 -> 16.432 | F12: =F2*'Drivers & Assumptons'!$C$28 -> 33.170023 | G12: =G2*'Drivers & Assumptons'!$C$28 -> 30.055671 | H12: =H2*'Drivers & Assumptons'!$C$28 -> 29.176861 | I12: =I2*'Drivers & Assumptons'!$C$28 -> 29.505523 | J12: =J2*'Drivers & Assumptons'!$C$28 -> 29.701889 | K12: =K2*'Drivers & Assumptons'!$C$28 -> 31.53775 | L12: =L2*'Drivers & Assumptons'!$C$28 -> 34.125719 | M12: =M2*'Drivers & Assumptons'!$C$28 -> 38.324188
A13: Marketing Expenses | B13: =78839/1000 -> 78.839 | C13: =36544/1000 -> 36.544 | D13: =17326/1000 -> 17.326 | E13: =11770/1000 -> 11.77 | F13: =F2*'Drivers & Assumptons'!$C$24 -> 24.958633 | G13: =G2*'Drivers & Assumptons'!$C$24 -> 22.615252 | H13: =H2*'Drivers & Assumptons'!$C$24 -> 21.953996 | I13: =I2*'Drivers & Assumptons'!$C$24 -> 22.201296 | J13: =J2*'Drivers & Assumptons'!$C$24 -> 22.349051 | K13: =K2*'Drivers & Assumptons'!$C$24 -> 23.730436 | L13: =L2*'Drivers & Assumptons'!$C$24 -> 25.677742 | M13: =M2*'Drivers & Assumptons'!$C$24 -> 28.836861
A14: Digital Assets (Gains) Losses and impairment | B14: =57436/1000 -> 57.436 | C14: =-13488/1000 -> -13.488 | D14: =-4251/1000 -> -4.251 | E14: =5577/1000 -> 5.577 | F14: =($B$14+$C$14+$D$14+$E$14)/4 -> 11.3185 | G14: =($B$14+$C$14+$D$14+$E$14)/4 -> 11.3185 | H14: =($B$14+$C$14+$D$14+$E$14)/4 -> 11.3185 | I14: =($B$14+$C$14+$D$14+$E$14)/4 -> 11.3185 | J14: =($B$14+$C$14+$D$14+$E$14)/4 -> 11.3185 | K14: =($B$14+$C$14+$D$14+$E$14)/4 -> 11.3185 | L14: =($B$14+$C$14+$D$14+$E$14)/4 -> 11.3185 | M14: =($B$14+$C$14+$D$14+$E$14)/4 -> 11.3185
A15: Gain on sale of intangible assets | B15: 0 | C15: =-21634/1000 -> -21.634 | D15: 0 | E15: 0 | F15: 0 | G15: 0 | H15: 0 | I15: 0 | J15: 0 | K15: 0 | L15: 0 | M15: 0
A16: Merger Termination Expenses | B16: =44194/1000 -> 44.194 | C16: 0 | D16: 0 | E16: 0 | F16: 0 | G16: 0 | H16: 0 | I16: 0 | J16: 0 | K16: 0 | L16: 0 | M16: 0
A17: Implied Total Operating Expenses | B17: =SUM(B9:B16) -> 500.814 | C17: =SUM(C9:C16) -> 453.214 | D17: =SUM(D9:D16) -> 491.731 | E17: =SUM(E9:E16) -> 714.704 | F17: =SUM(F9:F16) -> 751.44179 | G17: =SUM(G9:G16) -> 681.9512 | H17: =SUM(H9:H16) -> 662.3423 | I17: =SUM(I9:I16) -> 669.67575 | ... M17: =SUM(M9:M16) -> 866.44677
A18: Total Operating Expenses | B18: =500814/1000 -> 500.814 | C18: =453214/1000 -> 453.214 | D18: =491731/1000 -> 491.731 | E18: =714704/1000 -> 714.704 | F18: =SUM(F9:F16) -> 751.44179 | G18: =SUM(G9:G16) -> 681.9512 | H18: =SUM(H9:H16) -> 662.3423 | I18: =SUM(I9:I16) -> 669.67575 | J18: =SUM(J9:J16) -> 674.05726 | K18: =SUM(K9:K16) -> 715.02085 | L18: =SUM(L9:L16) -> 772.76625 | M18: =SUM(M9:M16) -> 866.44677

Sheet P&L
A1: (in millions) | B1: ='Drivers & Assumptons'!C2 & "A" -> 2022A | C1: =LEFT(B1,4) + 1 & IF(LEFT(B1,4) + 1 <= 2024, "A", "E") -> 2023A | D1: =LEFT(C1,4) + 1 & IF(LEFT(C1,4) + 1 <= 2024, "A", "E") -> 2024A | E1: 2025 6M Actual | F1: =LEFT(D1,4) + 1 & IF(LEFT(D1,4) + 1 <= 2024, "A", "E") -> 2025E | G1: =LEFT(F1,4) + 1 & IF(LEFT(F1,4) + 1 <= 2024, "A", "E") -> 2026E | H1: =LEFT(G1,4) + 1 & IF(LEFT(G1,4) + 1 <= 2024, "A", "E") -> 2027E | I1: =LEFT(H1,4) + 1 & IF(LEFT(H1,4) + 1 <= 2024, "A", "E") -> 2028E | J1: =LEFT(I1,4) + 1 & IF(LEFT(I1,4) + 1 <= 2024, "A", "E") -> 2029E | K1: =LEFT(J1,4) + 1 & IF(LEFT(J1,4) + 1 <= 2024, "A", "E") -> 2030E | L1: =LEFT(K1,4) + 1 & IF(LEFT(K1,4) + 1 <= 2024, "A", "E") -> 2031E | M1: =LEFT(L1,4) + 1 & IF(LEFT(L1,4) + 1 <= 2024, "A", "E") -> 2032E
A2: Total Revenue | B2: ='Revenue Build'!B29 -> 772.052 | C2: ='Revenue Build'!C29 -> 1450.466 | D2: ='Revenue Build'!D29 -> 1676.253 | E2: ='Revenue Build'!E29 -> 1236.651 | F2: ='Revenue Build'!F29 -> 2495.8633 | G2: ='Revenue Build'!G29 -> 2261.5252 | H2: ='Revenue Build'!H29 -> 2195.3996 | I2: ='Revenue Build'!I29 -> 2220.1296 | ... M2: ='Revenue Build'!M29 -> 2883.6861
A4: Cost of Revenue
A5: Distribution & Transaction Costs | B5: ='Expense Build'!B3 -> 286.953 | C5: ='Expense Build'!C3 -> 719.806 | D5: ='Expense Build'!D3 -> 1010.811 | E5: ='Expense Build'!E3 -> 753.784 | F5: ='Expense Build'!F3 -> 1521.3199 | G5: ='Expense Build'!G3 -> 1378.4823 | H5: ='Expense Build'!H3 -> 1338.1763 | I5: ='Expense Build'!I3 -> 1353.2502 | ... M5: ='Expense Build'!M3 -> 1757.7121
A6: Other Costs | B6: ='Expense Build'!B4 -> 22.401 | C6: ='Expense Build'!C4 -> 7.918 | D6: ='Expense Build'!D4 -> 6.553 | E6: ='Expense Build'!E4 -> 0.805 | F6: ='Expense Build'!F4 -> 1.6246863 | G6: ='Expense Build'!G4 -> 1.4721436 | H6: ='Expense Build'!H4 -> 1.429099 | I6: ='Expense Build'!I4 -> 1.445197 | ... M6: ='Expense Build'!M4 -> 1.8771402
A7: Total Costs of Revenue | B7: ='Expense Build'!B6 -> 309.354 | C7: ='Expense Build'!C6 -> 727.724 | D7: ='Expense Build'!D6 -> 1017.364 | E7: ='Expense Build'!E6 -> 754.589 | F7: ='Expense Build'!F6 -> 1522.9446 | G7: ='Expense Build'!G6 -> 1379.9545 | H7: ='Expense Build'!H6 -> 1339.6054 | I7: ='Expense Build'!I6 -> 1354.6954 | ... M7: ='Expense Build'!M6 -> 1759.5892
A9: Gross Profit
A10: Gross Profit | B10: =B2-B7 -> 462.698 | C10: =C2-C7 -> 722.742 | D10: =D2-D7 -> 658.889 | E10: =E2-E7 -> 482.062 | F10: =F2-F7 -> 972.91866 | G10: =G2-G7 -> 881.57078 | H10: =H2-H7 -> 855.79417 | I10: =I2-I7 -> 865.43426 | ... M10: =M2-M7 -> 1124.0968
A11: Gross Margin % | B11: =B10/B2 -> 0.59930937 | C11: =C10/C2 -> 0.49828262 | D11: =D10/D2 -> 0.39307253 | E11: =E10/E2 -> 0.38981249 | F11: =F10/F2 -> 0.38981249 | G11: =G10/G2 -> 0.38981249 | H11: =H10/H2 -> 0.38981249 | I11: =I10/I2 -> 0.38981249 | ... M11: =M10/M2 -> 0.38981249
A13: Opex
A14: Compensation Expenses | B14: ='Expense Build'!B9 -> 212.961 | C14: ='Expense Build'!C9 -> 296.055 | D14: ='Expense Build'!D9 -> 263.41 | E14: ='Expense Build'!E9 -> 579.012 | F14: ='Expense Build'!F9 -> 475.83633 | G14: ='Expense Build'!G9 -> 431.15979 | H14: ='Expense Build'!H9 -> 418.55293 | I14: ='Expense Build'!I9 -> 423.26772 | ... M14: ='Expense Build'!M9 -> 549.77475
A15: G&A Expenses | B15: ='Expense Build'!B10 -> 82.272 | C15: ='Expense Build'!C10 -> 100.128 | D15: ='Expense Build'!D10 -> 137.283 | E15: ='Expense Build'!E10 -> 73.824 | F15: ='Expense Build'!F10 -> 149.7518 | G15: ='Expense Build'!G10 -> 135.69151 | H15: ='Expense Build'!H10 -> 131.72398 | I15: ='Expense Build'!I10 -> 133.20778 | ... M15: ='Expense Build'!M10 -> 173.02116
A16: Depreciation & Amortization | B16: ='Expense Build'!B11 -> 13.277 | C16: ='Expense Build'!C11 -> 34.887 | D16: ='Expense Build'!D11 -> 50.854 | E16: ='Expense Build'!E11 -> 28.089 | F16: ='Expense Build'!F11 -> 56.40651 | G16: ='Expense Build'!G11 -> 51.110471 | H16: ='Expense Build'!H11 -> 49.616031 | I16: ='Expense Build'!I11 -> 50.17493 | ... M16: ='Expense Build'!M11 -> 65.171305
A17: IT Infrastructure Costs | B17: ='Expense Build'!B12 -> 11.835 | C17: ='Expense Build'!C12 -> 20.722 | D17: ='Expense Build'!D12 -> 27.109 | E17: ='Expense Build'!E12 -> 16.432 | F17: ='Expense Build'!F12 -> 33.170023 | G17: ='Expense Build'!G12 -> 30.055671 | H17: ='Expense Build'!H12 -> 29.176861 | I17: ='Expense Build'!I12 -> 29.505523 | ... M17: ='Expense Build'!M12 -> 38.324188
A18: Marketing Expenses | B18: ='Expense Build'!B13 -> 78.839 | C18: ='Expense Build'!C13 -> 36.544 | D18: ='Expense Build'!D13 -> 17.326 | E18: ='Expense Build'!E13 -> 11.77 | F18: ='Expense Build'!F13 -> 24.958633 | G18: ='Expense Build'!G13 -> 22.615252 | H18: ='Expense Build'!H13 -> 21.953996 | I18: ='Expense Build'!I13 -> 22.201296 | ... M18: ='Expense Build'!M13 -> 28.836861
A19: Digital Assets (Gains) / Losses | B19: ='Expense Build'!B14 -> 57.436 | C19: ='Expense Build'!C14 -> -13.488 | D19: ='Expense Build'!D14 -> -4.251 | E19: ='Expense Build'!E14 -> 5.577 | F19: ='Expense Build'!F14 -> 11.3185 | G19: ='Expense Build'!G14 -> 11.3185 | H19: ='Expense Build'!H14 -> 11.3185 | I19: ='Expense Build'!I14 -> 11.3185 | ... M19: ='Expense Build'!M14 -> 11.3185
A20: Gain on Sale of Intangible Assets | B20: ='Expense Build'!B15 -> 0 | C20: ='Expense Build'!C15 -> -21.634 | D20: ='Expense Build'!D15 -> 0 | E20: ='Expense Build'!E15 -> 0 | F20: ='Expense Build'!F15 -> 0 | G20: ='Expense Build'!G15 -> 0 | H20: ='Expense Build'!H15 -> 0 | I20: ='Expense Build'!I15 -> 0 | ... M20: ='Expense Build'!M15 -> 0
A21: Merger Termination Expenses | B21: ='Expense Build'!B16 -> 44.194 | C21: ='Expense Build'!C16 -> 0 | D21: ='Expense Build'!D16 -> 0 | E21: ='Expense Build'!E16 -> 0 | F21: ='Expense Build'!F16 -> 0 | G21: ='Expense Build'!G16 -> 0 | H21: ='Expense Build'!H16 -> 0 | I21: ='Expense Build'!I16 -> 0 | ... M21: ='Expense Build'!M16 -> 0
A22: Total Operating Expenses | B22: ='Expense Build'!B18 -> 500.814 | C22: ='Expense Build'!C18 -> 453.214 | D22: ='Expense Build'!D18 -> 491.731 | E22: ='Expense Build'!E18 -> 714.704 | F22: ='Expense Build'!F18 -> 751.44179 | G22: ='Expense Build'!G18 -> 681.9512 | H22: ='Expense Build'!H18 -> 662.3423 | I22: ='Expense Build'!I18 -> 669.67575 | ... M22: ='Expense Build'!M18 -> 866.44677
A24: Operating Income (EBIT)
A25: Implied EBIT | B25: =B10-B22 -> -38.116 | C25: =C10-C22 -> 269.528 | D25: =D10-D22 -> 167.158 | E25: =E10-E22 -> -232.642 | F25: =F10-F22 -> 221.47687 | G25: =G10-G22 -> 199.61958 | H25: =H10-H22 -> 193.45188 | I25: =I10-I22 -> 195.75851 | ... M25: =M10-M22 -> 257.65007
A26: EBIT | B26: =-38116/1000 -> -38.116 | C26: =269528/1000 -> 269.528 | D26: =167158/1000 -> 167.158 | E26: =-232642/1000 -> -232.642 | F26: =F10-F22 -> 221.47687 | G26: =G10-G22 -> 199.61958 | H26: =H10-H22 -> 193.45188 | I26: =I10-I22 -> 195.75851 | J26: =J10-J22 -> 197.13665 | K26: =K10-K22 -> 210.02118 | L26: =L10-L22 -> 228.18418 | M26: =M10-M22 -> 257.65007
A27: EBIT Margin % | B27: =B25/B2 -> -0.049369732 | C27: =C25/C2 -> 0.18582166 | D27: =D25/D2 -> 0.099721223 | E27: =E25/E2 -> -0.1881226 | F27: =F25/F2 -> 0.088737582 | G27: =G25/G2 -> 0.088267677 | H27: =H25/H2 -> 0.088116932 | I27: =I25/I2 -> 0.08817436 | ... M27: =M25/M2 -> 0.089347474
A29: Non-Operating
A30: True Interest Income | B30: =AVERAGE((D30/D33),(E30/E33))*B33 -> -183.11498 | C30: =AVERAGE((D30/D33),(E30/E33))*C33 -> 12.562206 | D30: =(33626/1000) -> 33.626 | E30: =17917/1000 -> 17.917 | F30: =E30*2 -> 35.834 | G30: =F30 -> 35.834 | H30: =G30 -> 35.834 | I30: =H30 -> 35.834 | J30: =I30 -> 35.834 | K30: =J30 -> 35.834 | L30: =K30 -> 35.834 | M30: =L30 -> 35.834
A31: Interest Expense | B31: =AVERAGE((D31/D33),(E31/E33))*B33 -> 11.756221 | C31: =AVERAGE((D31/D33),(E31/E33))*C33 -> -0.80651005 | D31: =-2002/1000 -> -2.002 | E31: =-679/1000 -> -0.679 | F31: =E31*2 -> -1.358 | G31: =F31 -> -1.358 | H31: =G31 -> -1.358 | I31: =H31 -> -1.358 | J31: =I31 -> -1.358 | K31: =J31 -> -1.358 | L31: =K31 -> -1.358 | M31: =L31 -> -1.358
A32: Other Non-Operating Gains/(Losses) | B32: =AVERAGE((D32/D33),(E32/E33))*B33 -> -549.03424 | C32: =AVERAGE((D32/D33),(E32/E33))*C33 -> 37.665304 | D32: =D33-(D30+D31) -> 22.792 | E32: =E33-(E30+E31) -> -180.762 | F32: =E32/2 -> -90.381 | G32: =F32 -> -90.381 | H32: =G32 -> -90.381 | I32: =H32 -> -90.381 | J32: =I32 -> -90.381 | K32: =J32 -> -90.381 | L32: =K32 -> -90.381 | M32: =L32 -> -90.381
A33: Total Other Non-Operating (Expense)/Income | B33: =-720393/1000 -> -720.393 | C33: =49421/1000 -> 49.421 | D33: =54416/1000 -> 54.416 | E33: =-163524/1000 -> -163.524 | F33: =F30+F31+F32 -> -55.905 | G33: =F33 -> -55.905 | H33: =G33 -> -55.905 | I33: =H33 -> -55.905 | J33: =I33 -> -55.905 | K33: =J33 -> -55.905 | L33: =K33 -> -55.905 | M33: =L33 -> -55.905
A35: Pre-Tax Income
A36: Implied EBT | B36: =B26+B33 -> -758.509 | C36: =C26+C33 -> 318.949 | D36: =D26+D33 -> 221.574 | E36: =E26+E33 -> -396.166 | F36: =F25+F33 -> 165.57187 | G36: =G25+G33 -> 143.71458 | H36: =H25+H33 -> 137.54688 | I36: =I25+I33 -> 139.85351 | J36: =J25+J33 -> 141.23165 | K36: =K25+K33 -> 154.11618 | L36: =L25+L33 -> 172.27918 | M36: =M25+M33 -> 201.74507
A37: EBT | B37: =-758509/1000 -> -758.509 | C37: =318949/1000 -> 318.949 | D37: =221574/1000 -> 221.574 | E37: =-396166/1000 -> -396.166 | F37: =F26+F33 -> 165.57187 | G37: =G26+G33 -> 143.71458 | H37: =H26+H33 -> 137.54688 | I37: =I26+I33 -> 139.85351 | J37: =J26+J33 -> 141.23165 | K37: =K26+K33 -> 154.11618 | L37: =L26+L33 -> 172.27918 | M37: =M26+M33 -> 201.74507
A39: Taxes
A40: Income Tax Expense | B40: =3263/1000 -> 3.263 | C40: =47400/1000 -> 47.4 | D40: =64583/1000 -> 64.583 | E40: =21143/1000 -> 21.143 | F40: =E40*2 -> 42.286 | G40: =F40 -> 42.286 | H40: =G40 -> 42.286 | I40: =H40 -> 42.286 | J40: =I40 -> 42.286 | K40: =J40 -> 42.286 | L40: =K40 -> 42.286 | M40: =L40 -> 42.286
A42: NOPAT
A43: NOPAT | B43: =B26*(1-'Drivers & Assumptons'!$C$18) -> -30.11164 | C43: =C26*(1-'Drivers & Assumptons'!$C$18) -> 212.92712 | D43: =D26*(1-'Drivers & Assumptons'!$C$18) -> 132.05482 | E43: =E26*(1-'Drivers & Assumptons'!$C$18) -> -183.78718 | F43: =F26*(1-'Drivers & Assumptons'!$C$18) -> 174.96673 | G43: =G26*(1-'Drivers & Assumptons'!$C$18) -> 157.69947 | H43: =H26*(1-'Drivers & Assumptons'!$C$18) -> 152.82698 | I43: =I26*(1-'Drivers & Assumptons'!$C$18) -> 154.64922 | ... M43: =M26*(1-'Drivers & Assumptons'!$C$18) -> 203.54355
A44: Loss from Discontinued Operations | B44: =-7075/1000 -> -7.075 | C44: =-3987/1000 -> -3.987 | D44: =-1324/1000 -> -1.324 | E44: 0 | F44: =E44 -> 0 | G44: =F44 -> 0 | H44: =G44 -> 0 | I44: =H44 -> 0 | J44: =I44 -> 0 | K44: =J44 -> 0 | L44: =K44 -> 0 | M44: =L44 -> 0
A46: Net Income
A47: Implied Net Income | B47: =B37-B40+B44 -> -768.847 | C47: =C37-C40+C44 -> 267.562 | D47: =D37-D40+D44 -> 155.667 | E47: =E37-E40+E44 -> -417.309 | F47: =F36-F40 -> 123.28587 | G47: =G36-G40 -> 101.42858 | H47: =H36-H40 -> 95.260877 | I47: =I36-I40 -> 97.56751 | J47: =J36-J40 -> 98.945652 | K47: =K36-K40 -> 111.83018 | L47: =L36-L40 -> 129.99318 | M47: =M36-M40 -> 159.45907
A48: Net Income | B48: =-768847/1000 -> -768.847 | C48: =267562/1000 -> 267.562 | D48: =155667/1000 -> 155.667 | E48: =-417309/1000 -> -417.309 | F48: =F37-F40 -> 123.28587 | G48: =G37-G40 -> 101.42858 | H48: =H37-H40 -> 95.260877 | I48: =I37-I40 -> 97.56751 | J48: =J37-J40 -> 98.945652 | K48: =K37-K40 -> 111.83018 | L48: =L37-L40 -> 129.99318 | M48: =M37-M40 -> 159.45907
A49: Net Income Margin % | B49: =B48/B2 -> -0.99584873 | C49: =C48/C2 -> 0.18446623 | D49: =D48/D2 -> 0.092866053 | E49: =E48/E2 -> -0.33745091 | F49: =F48/F2 -> 0.049396083 | G49: =G48/G2 -> 0.044849635 | H49: =H48/H2 -> 0.043391134 | I49: =I48/I2 -> 0.043946763 | ... M49: =M48/M2 -> 0.055296958
A51: Adjusted EBITDA | B51: 96 | C51: 395 | D51: 285 | E51: 248 | F51: =F2*E52 -> 500.52447 | G51: =G2*G52 -> 476.1452 | H51: =H2*H52 -> 484.17699 | I51: =I2*I52 -> 511.83229 | J51: =J2*J52 -> 537.5877 | K51: =K2*K52 -> 593.2609 | L51: =L2*L52 -> 641.94354 | M51: =M2*M52 -> 720.92152
A52: Adjusted Margin % | B52: =B51/B2 -> 0.12434396 | C52: =C51/C2 -> 0.27232627 | D52: =D51/D2 -> 0.17002207 | E52: =E51/E2 -> 0.20054162 | F52: =F51/F2 -> 0.20054162 | G52: =MIN(F52+0.01, 0.25) -> 0.21054162 | H52: =MIN(G52+0.01, 0.25) -> 0.22054162 | I52: =MIN(H52+0.01, 0.25) -> 0.23054162 | J52: =MIN(I52+0.01, 0.25) -> 0.24054162 | K52: =MIN(J52+0.01, 0.25) -> 0.25 | L52: =MIN(K52+0.01, 0.25) -> 0.25 | M52: =MIN(L52+0.01, 0.25) -> 0.25

Sheet Balance Sheet
A1: (in millions) | B1: 2023A | C1: 2024A | D1: 2025 6M Actual | E1: 2025E | F1: 2026E | G1: 2027E | H1: 2028E | I1: 2029E | J1: 2030E | K1: 2031E | L1: 2032E
A2: Assets
A3: Current Assets
A4: Cash & Cash Equivalents (including cash and cash equivalents segregated for corporate-held stablecoins) | B4: =644432/1000 -> 644.432 | C4: =1045474/1000 -> 1045.474 | D4: =1706390/1000 -> 1706.39 | E4: =SUM('Cash Flow Statement'!F56:F58) -> 1886.3126 | F4: =SUM('Cash Flow Statement'!G56:G58) -> 2003.5826 | G4: =SUM('Cash Flow Statement'!H56:H58) -> 2128.8787 | H4: =SUM('Cash Flow Statement'!I56:I58) -> 2263.526 | I4: =SUM('Cash Flow Statement'!J56:J58) -> 2408.4767 | J4: =SUM('Cash Flow Statement'!K56:K58) -> 2564.8186 | K4: =SUM('Cash Flow Statement'!L56:L58) -> 2733.8676 | L4: =SUM('Cash Flow Statement'!M56:M58) -> 2917.0033
A5: Cash & Cash Equivalents (segregated for the benefit of stablecoin holders) | B5: =24346152/1000 -> 24346.152 | C5: =43918572/1000 -> 43918.572 | D5: =61365920/1000 -> 61365.92 | E5: =D5*(1+'Drivers & Assumptons'!$C$34*0.5) -> 63820.557 | F5: =E5*(1+'Drivers & Assumptons'!$C$34) -> 68926.201 | G5: =F5*(1+'Drivers & Assumptons'!$C$34) -> 74440.297 | H5: =G5*(1+'Drivers & Assumptons'!$C$34) -> 80395.521 | I5: =H5*(1+'Drivers & Assumptons'!$C$34) -> 86827.163 | J5: =I5*(1+'Drivers & Assumptons'!$C$34) -> 93773.336 | K5: =J5*(1+'Drivers & Assumptons'!$C$34) -> 101275.2 | L5: =K5*(1+'Drivers & Assumptons'!$C$34) -> 109377.22
A6: Other/Reconciliation to Total Cash | B6: 0 | C6: 0 | D6: 0 | E6: ='Cash Flow Statement'!F60 -> 17565.491 | F6: ='Cash Flow Statement'!G60 -> 17519.525 | G6: ='Cash Flow Statement'!H60 -> 17411.405 | H6: ='Cash Flow Statement'!I60 -> 17265.616 | I6: ='Cash Flow Statement'!J60 -> 17087.956 | J6: ='Cash Flow Statement'!K60 -> 16887.242 | K6: ='Cash Flow Statement'!L60 -> 16679.093 | L6: ='Cash Flow Statement'!M60 -> 16478.574
A7: Implied Total Cash & CE from CFS | B7: =SUM(B4:B5) -> 24990.584 | C7: =SUM(C4:C5) -> 44964.046 | D7: =SUM(D4:D5) -> 63072.31 | E7: ='Cash Flow Statement'!F62 -> 83272.36 | F7: ='Cash Flow Statement'!G62 -> 88449.309 | G7: ='Cash Flow Statement'!H62 -> 93980.582 | H7: ='Cash Flow Statement'!I62 -> 99924.663 | I7: ='Cash Flow Statement'!J62 -> 106323.6 | J7: ='Cash Flow Statement'!K62 -> 113225.4 | K7: ='Cash Flow Statement'!L62 -> 120688.16 | L7: ='Cash Flow Statement'!M62 -> 128772.8
A8: Total Cash & CE | B8: =SUM(B4:B5) -> 24990.584 | C8: =SUM(C4:C5) -> 44964.046 | D8: =SUM(D4:D5) -> 63072.31 | E8: =SUM(E4:E5) -> 65706.869 | F8: =SUM(F4:F5) -> 70929.784 | G8: =SUM(G4:G5) -> 76569.176 | H8: =SUM(H4:H5) -> 82659.047 | I8: =SUM(I4:I5) -> 89235.64 | ... L8: =SUM(L4:L5) -> 112294.22
A9: Available-for-sale debt securities, at fair value | B9: =152183/1000 -> 152.183 | C9: 0 | D9: 0 | E9: 0 | F9: 0 | G9: 0 | H9: 0 | I9: 0 | J9: 0 | K9: 0 | L9: 0
A10: Accounts receivable, net | B10: =1940/1000 -> 1.94 | C10: =6418/1000 -> 6.418 | D10: =13215/1000 -> 13.215 | E10: ='P&L'!F2*'Drivers & Assumptons'!$C$35 -> 18.113599 | F10: ='P&L'!G2*'Drivers & Assumptons'!$C$35 -> 16.412903 | G10: ='P&L'!H2*'Drivers & Assumptons'!$C$35 -> 15.932999 | H10: ='P&L'!I2*'Drivers & Assumptons'!$C$35 -> 16.112476 | I10: ='P&L'!J2*'Drivers & Assumptons'!$C$35 -> 16.219708 | J10: ='P&L'!K2*'Drivers & Assumptons'!$C$35 -> 17.222242 | K10: ='P&L'!L2*'Drivers & Assumptons'!$C$35 -> 18.635489 | L10: ='P&L'!M2*'Drivers & Assumptons'!$C$35 -> 20.928203
A11: Stablecoins receivable, net | B11: =22559/1000 -> 22.559 | C11: =6957/1000 -> 6.957 | D11: 0 | E11: 0 | F11: 0 | G11: 0 | H11: 0 | I11: 0 | J11: 0 | K11: 0 | L11: 0
A12: Prepaid expenses and other current assets | B12: =146645/1000 -> 146.645 | C12: =187528/1000 -> 187.528 | D12: =216604/1000 -> 216.604 | E12: ='P&L'!F22*'Drivers & Assumptons'!$C$38 -> 252.48391 | F12: ='P&L'!G22*'Drivers & Assumptons'!$C$38 -> 229.13512 | G12: ='P&L'!H22*'Drivers & Assumptons'!$C$38 -> 222.54655 | H12: ='P&L'!I22*'Drivers & Assumptons'!$C$38 -> 225.01058 | I12: ='P&L'!J22*'Drivers & Assumptons'!$C$38 -> 226.48276 | J12: ='P&L'!K22*'Drivers & Assumptons'!$C$38 -> 240.24651 | K12: ='P&L'!L22*'Drivers & Assumptons'!$C$38 -> 259.64892 | L12: ='P&L'!M22*'Drivers & Assumptons'!$C$38 -> 291.12551
A13: Total Operating Current Assets | B13: =SUM(B10,B11,B12) -> 171.144 | C13: =SUM(C10,C11,C12) -> 200.903 | D13: =SUM(D10,D11,D12) -> 229.819 | E13: =SUM(E10,E11,E12) -> 270.59751 | F13: =SUM(F10,F11,F12) -> 245.54803 | G13: =SUM(G10,G11,G12) -> 238.47955 | H13: =SUM(H10,H11,H12) -> 241.12306 | I13: =SUM(I10,I11,I12) -> 242.70247 | ... L13: =SUM(L10,L11,L12) -> 312.05371
A14: Non-Current Assets
A15: Available-for-sale debt securities, at fair value | B15: =87940/1000 -> 87.94 | C15: 0 | D15: 0 | E15: 0 | F15: 0 | G15: 0 | H15: 0 | I15: 0 | J15: 0 | K15: 0 | L15: 0
A16: Investments | B16: =75874/1000 -> 75.874 | C16: =84114/1000 -> 84.114 | D16: =83794/1000 -> 83.794 | E16: =D16 -> 83.794 | F16: =E16 -> 83.794 | G16: =F16 -> 83.794 | H16: =G16 -> 83.794 | I16: =H16 -> 83.794 | J16: =I16 -> 83.794 | K16: =J16 -> 83.794 | L16: =K16 -> 83.794
A17: Fixed assets, net | B17: =2619/1000 -> 2.619 | C17: =18682/1000 -> 18.682 | D17: =23804/1000 -> 23.804 | E17: =D17*(1+'Drivers & Assumptons'!C40) -> 28.5648 | F17: =E17*(1+'Drivers & Assumptons'!$C$39) -> 29.298698 | G17: =F17*(1+'Drivers & Assumptons'!$C$39) -> 30.051451 | H17: =G17*(1+'Drivers & Assumptons'!$C$39) -> 30.823544 | I17: =H17*(1+'Drivers & Assumptons'!$C$39) -> 31.615474 | J17: =I17*(1+'Drivers & Assumptons'!$C$39) -> 32.427751 | K17: =J17*(1+'Drivers & Assumptons'!$C$39) -> 33.260897 | L17: =K17*(1+'Drivers & Assumptons'!$C$39) -> 34.115449
A18: Digital assets | B18: =11339/1000 -> 11.339 | C18: =31330/1000 -> 31.33 | D18: =35113/1000 -> 35.113 | E18: =D18 -> 35.113 | F18: =E18 -> 35.113 | G18: =F18 -> 35.113 | H18: =G18 -> 35.113 | I18: =H18 -> 35.113 | J18: =I18 -> 35.113 | K18: =J18 -> 35.113 | L18: =K18 -> 35.113
A19: Goodwill | B19: 0 | C19: =169544/1000 -> 169.544 | D19: =266384/1000 -> 266.384 | E19: =D19 -> 266.384 | F19: =E19 -> 266.384 | G19: =F19 -> 266.384 | H19: =G19 -> 266.384 | I19: =H19 -> 266.384 | J19: =I19 -> 266.384 | K19: =J19 -> 266.384 | L19: =K19 -> 266.384
A20: Intangible Assets, net | B20: 0 | C20: =331394/1000 -> 331.394 | D20: =396969/1000 -> 396.969 | E20: =D20 -> 396.969 | F20: =E20 -> 396.969 | G20: =F20 -> 396.969 | H20: =G20 -> 396.969 | I20: =H20 -> 396.969 | J20: =I20 -> 396.969 | K20: =J20 -> 396.969 | L20: =K20 -> 396.969
A21: Deferred tax assets, net | B21: 0 | C21: =10223/1000 -> 10.223 | D21: 0 | E21: 0 | F21: 0 | G21: 0 | H21: 0 | I21: 0 | J21: 0 | K21: 0 | L21: 0
A22: Other non-current assets | B22: =4400/1000 -> 4.4 | C22: =20615/1000 -> 20.615 | D22: 0 | E22: 0 | F22: 0 | G22: 0 | H22: 0 | I22: 0 | J22: 0 | K22: 0 | L22: 0
A23: Other Assets/ Rounding Adjustment Plug | B23: =B42-SUM(B15:B22,B8:B12) -> -629.903 | C23: =C42-SUM(C15:C22,C8:C12) -> 15.357 | D23: =D42-SUM(D15:D22,D8:D12) -> -9.632 | E23: =E42-SUM(E15:E22,E8:E12) -> -129.61867 | F23: =F42-SUM(F15:F22,F8:F12) -> -218.09659 | G23: =G42-SUM(G15:G22,G8:G12) -> -523.5652 | H23: =H42-SUM(H15:H22,H8:H12) -> -586.89345 | I23: =I42-SUM(I15:I22,I8:I12) -> -661.2927 | ... L23: =L42-SUM(L15:L22,L8:L12) -> -863.42298
A24: Total Assets | B24: =SUM(B15:B23,B8:B12) -> 24866.18 | C24: =SUM(C15:C23,C8:C12) -> 45846.208 | D24: =SUM(D15:D23,D8:D12) -> 64098.561 | E24: =SUM(E15:E23,E8:E12) -> 66658.673 | F24: =SUM(F15:F23,F8:F12) -> 71768.794 | G24: =SUM(G15:G23,G8:G12) -> 77096.402 | H24: =SUM(H15:H23,H8:H12) -> 83126.36 | I24: =SUM(I15:I23,I8:I12) -> 89630.925 | ... L24: =SUM(L15:L23,L8:L12) -> 112559.23
A26: Liabilities, Redeemable Convertible Preferred Stock and Stockholders' Equity
A27: Current Liabilities
A28: Deferred Revenue | B28: =2499/1000 -> 2.499 | C28: =13390/1000 -> 13.39 | D28: =8507/1000 -> 8.507 | E28: =D28 -> 8.507 | F28: ='P&L'!G2*'Drivers & Assumptons'!$C$42 -> 12.506243 | G28: ='P&L'!H2*'Drivers & Assumptons'!$C$42 -> 12.140568 | H28: ='P&L'!I2*'Drivers & Assumptons'!$C$42 -> 12.277326 | I28: ='P&L'!J2*'Drivers & Assumptons'!$C$42 -> 12.359034 | J28: ='P&L'!K2*'Drivers & Assumptons'!$C$42 -> 13.122941 | K28: ='P&L'!L2*'Drivers & Assumptons'!$C$42 -> 14.199801 | L28: ='P&L'!M2*'Drivers & Assumptons'!$C$42 -> 15.946795
A29: Accounts payable and accrued expenses | B29: =152586/1000 -> 152.586 | C29: =287007/1000 -> 287.007 | D29: =411560/1000 -> 411.56 | E29: ='P&L'!F22*'Drivers & Assumptons'!$C$37 -> 374.76628 | F29: =0.5*('P&L'!G22*'Drivers & Assumptons'!C37)+0.5*(('P&L'!G22-'P&L'!G16-'Cash Flow Statement'!G17)*'Drivers & Assumptons'!C37) -> 295.8127 | G29: =('P&L'!H22-'Cash Flow Statement'!H17-'P&L'!H16)*'Drivers & Assumptons'!$C$37 -> 244.32702 | H29: =('P&L'!I22-'Cash Flow Statement'!I17-'P&L'!I16)*'Drivers & Assumptons'!$C$37 -> 247.01565 | I29: =('P&L'!J22-'Cash Flow Statement'!J17-'P&L'!J16)*'Drivers & Assumptons'!$C$37 -> 248.62202 | J29: =('P&L'!K22-'Cash Flow Statement'!K17-'P&L'!K16)*'Drivers & Assumptons'!$C$37 -> 263.64034 | K29: =('P&L'!L22-'Cash Flow Statement'!L17-'P&L'!L16)*'Drivers & Assumptons'!$C$37 -> 284.81129 | L29: =('P&L'!M22-'Cash Flow Statement'!M17-'P&L'!M16)*'Drivers & Assumptons'!$C$37 -> 319.15699
A30: Obligations to return digital asset collateral | B30: =4662/1000 -> 4.662 | C30: =570/1000 -> 0.57 | D30: 0 | E30: 0 | F30: 0 | G30: 0 | H30: 0 | I30: 0 | J30: 0 | K30: 0 | L30: 0
A31: Deposits from stablecoin holders | B31: =24276065/1000 -> 24276.065 | C31: =43727363/1000 -> 43727.363 | D31: =61101523/1000 -> 61101.523 | E31: =D31*(1+'Drivers & Assumptons'!$C$5*0.5) -> 63545.584 | F31: =E31*(1+'Drivers & Assumptons'!$C$5) -> 68629.231 | G31: =F31*(1+'Drivers & Assumptons'!$C$5) -> 74119.569 | H31: =G31*(1+'Drivers & Assumptons'!$C$5) -> 80049.135 | I31: =H31*(1+'Drivers & Assumptons'!$C$5) -> 86453.065 | J31: =I31*(1+'Drivers & Assumptons'!$C$5) -> 93369.311 | K31: =J31*(1+'Drivers & Assumptons'!$C$5) -> 100838.86 | L31: =K31*(1+'Drivers & Assumptons'!$C$5) -> 108905.96
A32: Convertible debt, net of debt discount | B32: 0 | C32: 0 | D32: =206140/1000 -> 206.14 | E32: =D32 -> 206.14 | F32: =E32 -> 206.14 | G32: 0 | H32: 0 | I32: 0 | J32: 0 | K32: 0 | L32: 0
A33: Other current liabilities | B33: =4225/1000 -> 4.225 | C33: =16027/1000 -> 16.027 | D33: 0 | E33: 0 | F33: 0 | G33: 0 | H33: 0 | I33: 0 | J33: 0 | K33: 0 | L33: 0
A34: Total Operating Current Liabilities | B34: =SUM(B28,B29,B33) -> 159.31 | C34: =SUM(C28,C29,C33) -> 316.424 | D34: =SUM(D28,D29,D33) -> 420.067 | E34: =SUM(E28,E29,E33) -> 383.27328 | F34: =SUM(F28,F29,F33) -> 308.31895 | G34: =SUM(G28,G29,G33) -> 256.46759 | H34: =SUM(H28,H29,H33) -> 259.29298 | I34: =SUM(I28,I29,I33) -> 260.98106 | ... L34: =SUM(L28,L29,L33) -> 335.10379
A35: Non-Current Liabilities
A36: Convertible debt, net of debt discount | B36: =58487/1000 -> 58.487 | C36: =40717/1000 -> 40.717 | D36: 0 | E36: 0 | F36: 0 | G36: 0 | H36: 0 | I36: 0 | J36: 0 | K36: 0 | L36: 0
A37: Deferred tax liabilities, net | B37: =19616/1000 -> 19.616 | C37: =29559/1000 -> 29.559 | D37: 0 | E37: =C37 -> 29.559 | F37: =E37 -> 29.559 | G37: =F37 -> 29.559 | H37: =G37 -> 29.559 | I37: =H37 -> 29.559 | J37: =I37 -> 29.559 | K37: =J37 -> 29.559 | L37: =K37 -> 29.559
A38: Other non-current liabilities | B38: =8569/1000 -> 8.569 | C38: =21281/1000 -> 21.281 | D38: 0 | E38: 0 | F38: 0 | G38: 0 | H38: 0 | I38: 0 | J38: 0 | K38: 0 | L38: 0
A39: Redeemable convertible preferred stock | B39: 0 | C39: =1139765/1000 -> 1139.765 | D39: 0 | E39: 0 | F39: 0 | G39: 0 | H39: 0 | I39: 0 | J39: 0 | K39: 0 | L39: 0
A40: Stockholders' Equity
A41: Total stockholders' equity | B41: =339471/1000 -> 339.471 | C41: =570529/1000 -> 570.529 | D41: =2370831/1000 -> 2370.831 | E41: =D41+'P&L'!F48 -> 2494.1169 | F41: =E41+'P&L'!G48 -> 2595.5455 | G41: =F41+'P&L'!H48 -> 2690.8063 | H41: =G41+'P&L'!I48 -> 2788.3738 | I41: =H41+'P&L'!J48 -> 2887.3195 | J41: =I41+'P&L'!K48 -> 2999.1497 | K41: =J41+'P&L'!L48 -> 3129.1428 | L41: =K41+'P&L'!M48 -> 3288.6019
A42: Total Liabilities and Stockholders' Equity | B42: =SUM(B36:B41,B28:B33) -> 24866.18 | C42: =SUM(C36:C41,C28:C33) -> 45846.208 | D42: =SUM(D36:D41,D28:D33) -> 64098.561 | E42: =SUM(E36:E41,E28:E33) -> 66658.673 | F42: =SUM(F36:F41,F28:F33) -> 71768.794 | G42: =SUM(G36:G41,G28:G33) -> 77096.402 | H42: =SUM(H36:H41,H28:H33) -> 83126.36 | I42: =SUM(I36:I41,I28:I33) -> 89630.925 | ... L42: =SUM(L36:L41,L28:L33) -> 112559.23

Sheet Cash Flow Statement
A1: (in millions) | B1: 2022A | C1: 2023A | D1: 2024A | E1: 2025 6M Actual | F1: 2025E | G1: 2026E | H1: 2027E | I1: 2028E | J1: 2029E | K1: 2030E | L1: 2031E | M1: 2032E
A2: Cash flows from operating activities
A3: Net income (loss) | B3: ='P&L'!B48 -> -768.847 | C3: ='P&L'!C48 -> 267.562 | D3: ='P&L'!D48 -> 155.667 | E3: ='P&L'!E48 -> -417.309 | F3: ='P&L'!F48 -> 123.28587 | G3: ='P&L'!G48 -> 101.42858 | H3: ='P&L'!H48 -> 95.260877 | I3: ='P&L'!I48 -> 97.56751 | ... M3: ='P&L'!M48 -> 159.45907
A4: Adjustments to reconcile net income (loss) to net cash provided by (used in) operating activities:
A5: Depreciation and amortization expense | B5: =13277/1000 -> 13.277 | C5: =34887/1000 -> 34.887 | D5: =50854/1000 -> 50.854 | E5: =28089/1000 -> 28.089 | F5: ='Expense Build'!F11 -> 56.40651 | G5: ='Expense Build'!G11 -> 51.110471 | H5: ='Expense Build'!H11 -> 49.616031 | I5: ='Expense Build'!I11 -> 50.17493 | J5: ='Expense Build'!J11 -> 50.508855 | K5: ='Expense Build'!K11 -> 53.630786 | L5: ='Expense Build'!L11 -> 58.031696 | M5: ='Expense Build'!M11 -> 65.171305
A6: Accretion of premium on available-for-sale debt securities | B6: =-353422/1000 -> -353.422 | C6: =-7738/1000 -> -7.738 | D6: =-2268/1000 -> -2.268 | E6: 0 | F6: 0 | G6: 0 | H6: 0 | I6: 0 | J6: 0 | K6: 0 | L6: 0 | M6: 0
A7: Realized and unrealized (gains) losses on digital assets | B7: =269277/1000 -> 269.277 | C7: =-13010/1000 -> -13.01 | D7: =-12878/1000 -> -12.878 | E7: =7189/1000 -> 7.189 | F7: 0 | G7: 0 | H7: 0 | I7: 0 | J7: 0 | K7: 0 | L7: 0 | M7: 0
A8: Change in fair value of convertible debt, warrant liability, and embedded derivatives | B8: =486938/1000 -> 486.938 | C8: =-25343/1000 -> -25.343 | D8: =-10024/1000 -> -10.024 | E8: =170106/1000 -> 170.106 | F8: 0 | G8: 0 | H8: 0 | I8: 0 | J8: 0 | K8: 0 | L8: 0 | M8: 0
A9: Digital assets received for services | B9: =-7235/1000 -> -7.235 | C9: =-4476/1000 -> -4.476 | D9: =-1500/1000 -> -1.5 | E9: =-9416/1000 -> -9.416 | F9: 0 | G9: 0 | H9: 0 | I9: 0 | J9: 0 | K9: 0 | L9: 0 | M9: 0
A10: Equity securities received for services | B10: 0 | C10: 0 | D10: 0 | E10: =-3826/1000 -> -3.826 | F10: 0 | G10: 0 | H10: 0 | I10: 0 | J10: 0 | K10: 0 | L10: 0 | M10: 0
A11: Deferred taxes | B11: =-786/1000 -> -0.786 | C11: =-32893/1000 -> -32.893 | D11: =-2806/1000 -> -2.806 | E11: =-5751/1000 -> -5.751 | F11: 0 | G11: 0 | H11: 0 | I11: 0 | J11: 0 | K11: 0 | L11: 0 | M11: 0
A12: Realized and unrealized (gains) losses on available-for-sale debt securities and strategic investments | B12: =26877/1000 -> 26.877 | C12: =1749/1000 -> 1.749 | D12: =-434/1000 -> -0.434 | E12: =1416/1000 -> 1.416 | F12: 0 | G12: 0 | H12: 0 | I12: 0 | J12: 0 | K12: 0 | L12: 0 | M12: 0
A13: Gain on sale of long-lived assets | B13: 0 | C13: =-21521/1000 -> -21.521 | D13: 0 | E13: 0 | F13: 0 | G13: 0 | H13: 0 | I13: 0 | J13: 0 | K13: 0 | L13: 0 | M13: 0
A14: Foreign currency remeasurement | B14: 0 | C14: 0 | D14: 0 | E14: =8763/1000 -> 8.763 | F14: 0 | G14: 0 | H14: 0 | I14: 0 | J14: 0 | K14: 0 | L14: 0 | M14: 0
A15: Provisions for warrants in common stock | B15: 0 | C15: 0 | D15: 0 | E15: =5565/1000 -> 5.565 | F15: 0 | G15: 0 | H15: 0 | I15: 0 | J15: 0 | K15: 0 | L15: 0 | M15: 0
A16: Shares issued for merger-termination | B16: =15520/1000 -> 15.52 | C16: 0 | D16: 0 | E16: 0 | F16: 0 | G16: 0 | H16: 0 | I16: 0 | J16: 0 | K16: 0 | L16: 0 | M16: 0
A17: Stock-based compensation | B17: =69266/1000 -> 69.266 | C17: =107999/1000 -> 107.999 | D17: =50134/1000 -> 50.134 | E17: =447682/1000 -> 447.682 | F17: =E17*2 -> 895.364 | G17: ='Expense Build'!G9*'Drivers & Assumptons'!$C$44 -> 126.52709 | H17: ='Expense Build'!H9*'Drivers & Assumptons'!$C$44 -> 122.82751 | I17: ='Expense Build'!I9*'Drivers & Assumptons'!$C$44 -> 124.2111 | J17: ='Expense Build'!J9*'Drivers & Assumptons'!$C$44 -> 125.03775 | K17: ='Expense Build'!K9*'Drivers & Assumptons'!$C$44 -> 132.76628 | L17: ='Expense Build'!L9*'Drivers & Assumptons'!$C$44 -> 143.66101 | M17: ='Expense Build'!M9*'Drivers & Assumptons'!$C$44 -> 161.33554
A18: Other non-cash items | B18: =5547/1000 -> 5.547 | C18: =4811/1000 -> 4.811 | D18: 0 | E18: =2306/1000 -> 2.306 | F18: =E18 -> 2.306 | G18: =F18 -> 2.306 | H18: =G18 -> 2.306 | I18: =H18 -> 2.306 | J18: =I18 -> 2.306 | K18: =J18 -> 2.306 | L18: =K18 -> 2.306 | M18: =L18 -> 2.306
A19: Changes in operating assets and liabilities:
A20: Accounts receivable | B20: =18735/1000 -> 18.735 | C20: =2244/1000 -> 2.244 | D20: =-4569/1000 -> -4.569 | E20: =-8635/1000 -> -8.635 | F20: =-('Balance Sheet'!E10-'Balance Sheet'!C10) -> -11.695599 | G20: =-('Balance Sheet'!F10-'Balance Sheet'!E10) -> 1.700696 | H20: =-('Balance Sheet'!G10-'Balance Sheet'!F10) -> 0.47990348 | I20: =-('Balance Sheet'!H10-'Balance Sheet'!G10) -> -0.17947706 | J20: =-('Balance Sheet'!I10-'Balance Sheet'!H10) -> -0.107232 | K20: =-('Balance Sheet'!J10-'Balance Sheet'!I10) -> -1.0025332 | L20: =-('Balance Sheet'!K10-'Balance Sheet'!J10) -> -1.413247 | M20: =-('Balance Sheet'!L10-'Balance Sheet'!K10) -> -2.2927143
A21: Prepaid expenses and other current assets | B21: =-77571/1000 -> -77.571 | C21: =-51161/1000 -> -51.161 | D21: =-21764/1000 -> -21.764 | E21: =-42104/1000 -> -42.104 | F21: =-('Balance Sheet'!E12-'Balance Sheet'!C12) -> -64.955915 | G21: =-('Balance Sheet'!F12-'Balance Sheet'!E12) -> 23.348791 | H21: =('Balance Sheet'!G12-'Balance Sheet'!F12)*-1 -> 6.5885765 | I21: =('Balance Sheet'!H12-'Balance Sheet'!G12)*-1 -> -2.4640337 | J21: =('Balance Sheet'!I12-'Balance Sheet'!H12)*-1 -> -1.472184 | K21: =('Balance Sheet'!J12-'Balance Sheet'!I12)*-1 -> -13.763741 | L21: =('Balance Sheet'!K12-'Balance Sheet'!J12)*-1 -> -19.402414 | M21: =('Balance Sheet'!L12-'Balance Sheet'!K12)*-1 -> -31.476587
A22: Accounts payable and accrued expenses | B22: =227300/1000 -> 227.3 | C22: =-123833/1000 -> -123.833 | D22: =132878/1000 -> 132.878 | E22: =123981/1000 -> 123.981 | F22: ='Balance Sheet'!E29-'Balance Sheet'!C29 -> 87.759277 | G22: =('Expense Build'!G9-'Cash Flow Statement'!G17-'Cash Flow Statement'!G5)*'Drivers & Assumptons'!$C$37 -> 126.43904 | H22: =('Expense Build'!H9-'Cash Flow Statement'!H17-'Cash Flow Statement'!H5)*'Drivers & Assumptons'!$C$37 -> 122.74204 | I22: =('Expense Build'!I9-'Cash Flow Statement'!I17-'Cash Flow Statement'!I5)*'Drivers & Assumptons'!$C$37 -> 124.12467 | J22: =('Expense Build'!J9-'Cash Flow Statement'!J17-'Cash Flow Statement'!J5)*'Drivers & Assumptons'!$C$37 -> 124.95074 | K22: =('Expense Build'!K9-'Cash Flow Statement'!K17-'Cash Flow Statement'!K5)*'Drivers & Assumptons'!$C$37 -> 132.6739 | L22: =('Expense Build'!L9-'Cash Flow Statement'!L17-'Cash Flow Statement'!L5)*'Drivers & Assumptons'!$C$37 -> 143.56104 | M22: =('Expense Build'!M9-'Cash Flow Statement'!M17-'Cash Flow Statement'!M5)*'Drivers & Assumptons'!$C$37 -> 161.22328
A23: Other current liabilities | B23: =2431/1000 -> 2.431 | C23: =291/1000 -> 0.291 | D23: =10891/1000 -> 10.891 | E23: =-4340/1000 -> -4.34 | F23: ='Balance Sheet'!E33-'Balance Sheet'!C33 -> -16.027 | G23: ='Balance Sheet'!F33-'Balance Sheet'!E33 -> 0 | H23: ='Balance Sheet'!G33-'Balance Sheet'!F33 -> 0 | I23: ='Balance Sheet'!H33-'Balance Sheet'!G33 -> 0 | J23: ='Balance Sheet'!I33-'Balance Sheet'!H33 -> 0 | K23: ='Balance Sheet'!J33-'Balance Sheet'!I33 -> 0 | L23: ='Balance Sheet'!K33-'Balance Sheet'!J33 -> 0 | M23: ='Balance Sheet'!L33-'Balance Sheet'!K33 -> 0
A24: Net cash provided by (used in) operating activities | B24: =SUM(B3:B23) -> -72.693 | C24: =SUM(C3:C23) -> 139.568 | D24: =SUM(D3:D23) -> 344.181 | E24: =SUM(E3:E23) -> 303.716 | F24: =SUM(F3:F23) -> 1072.4431 | G24: =SUM(G3:G23) -> 432.86067 | H24: =SUM(H3:H23) -> 399.82094 | I24: =SUM(I3:I23) -> 395.7407 | ... M24: =SUM(M3:M23) -> 515.72589
A26: Cash flows from investing activities
A27: Proceeds from sale of discontinued business | B27: =1000/1000 -> 1 | C27: 0 | D27: 0 | E27: 0 | F27: 0 | G27: 0 | H27: 0 | I27: 0 | J27: 0 | K27: 0 | L27: 0 | M27: 0
A28: Purchase of available-for-sale debt securities | B28: =-102850973/1000 -> -102850.97 | C28: =-311639/1000 -> -311.639 | D28: =-99313/1000 -> -99.313 | E28: 0 | F28: =-('Balance Sheet'!E31-'Balance Sheet'!C31) -> -19818.221 | G28: =-('Balance Sheet'!F31-'Balance Sheet'!E31) -> -5083.6467 | H28: =-('Balance Sheet'!G31-'Balance Sheet'!F31) -> -5490.3385 | I28: =-('Balance Sheet'!H31-'Balance Sheet'!G31) -> -5929.5655 | J28: =-('Balance Sheet'!I31-'Balance Sheet'!H31) -> -6403.9308 | K28: =-('Balance Sheet'!J31-'Balance Sheet'!I31) -> -6916.2452 | L28: =-('Balance Sheet'!K31-'Balance Sheet'!J31) -> -7469.5448 | M28: =-('Balance Sheet'!L31-'Balance Sheet'!K31) -> -8067.1084
A29: Sales and maturities of available-for-sale debt securities | B29: =94442236/1000 -> 94442.236 | C29: =8827550/1000 -> 8827.55 | D29: =341561/1000 -> 341.561 | E29: 0 | F29: ='Drivers & Assumptons'!$C$45*ABS(F28) -> 18827.31 | G29: ='Drivers & Assumptons'!$C$45*ABS(G28) -> 4829.4644 | H29: ='Drivers & Assumptons'!$C$45*ABS(H28) -> 5215.8215 | I29: ='Drivers & Assumptons'!$C$45*ABS(I28) -> 5633.0873 | J29: ='Drivers & Assumptons'!$C$45*ABS(J28) -> 6083.7342 | K29: ='Drivers & Assumptons'!$C$45*ABS(K28) -> 6570.433 | L29: ='Drivers & Assumptons'!$C$45*ABS(L28) -> 7096.0676 | M29: ='Drivers & Assumptons'!$C$45*ABS(M28) -> 7663.753
A30: Cash acquired from acquisition of equity method affiliate | B30: 0 | C30: =1629/1000 -> 1.629 | D30: 0 | E30: 0 | F30: 0 | G30: 0 | H30: 0 | I30: 0 | J30: 0 | K30: 0 | L30: 0 | M30: 0
A31: Sale and return of investments | B31: 0 | C31: =1107/1000 -> 1.107 | D31: =739/1000 -> 0.739 | E31: =194/1000 -> 0.194 | F31: 0 | G31: 0 | H31: 0 | I31: 0 | J31: 0 | K31: 0 | L31: 0 | M31: 0
A32: Purchase of investments | B32: =-16032/1000 -> -16.032 | C32: =-2661/1000 -> -2.661 | D32: =-4265/1000 -> -4.265 | E32: =-6370/1000 -> -6.37 | F32: 0 | G32: 0 | H32: 0 | I32: 0 | J32: 0 | K32: 0 | L32: 0 | M32: 0
A33: Business combinations, net of cash acquired | B33: =-43456/1000 -> -43.456 | C33: 0 | D33: 0 | E33: =-7734/1000 -> -7.734 | F33: 0 | G33: 0 | H33: 0 | I33: 0 | J33: 0 | K33: 0 | L33: 0 | M33: 0
A34: Proceeds from the sale of digital assets | B34: 0 | C34: =27301/1000 -> 27.301 | D34: =4805/1000 -> 4.805 | E34: =79/1000 -> 0.079 | F34: 0 | G34: 0 | H34: 0 | I34: 0 | J34: 0 | K34: 0 | L34: 0 | M34: 0
A35: Capitalization of software development costs | B35: =-18315/1000 -> -18.315 | C35: =-32862/1000 -> -32.862 | D35: =-39098/1000 -> -39.098 | E35: =-24858/1000 -> -24.858 | F35: =E35*2 -> -49.716 | G35: =F35 -> -49.716 | H35: =G35 -> -49.716 | I35: =H35 -> -49.716 | J35: =I35 -> -49.716 | K35: =J35 -> -49.716 | L35: =K35 -> -49.716 | M35: =L35 -> -49.716
A36: Purchase of long-lived assets | B36: =-3050/1000 -> -3.05 | C36: =-654/1000 -> -0.654 | D36: =-18128/1000 -> -18.128 | E36: =-7419/1000 -> -7.419 | F36: =2*E36 -> -14.838 | G36: =F36 -> -14.838 | H36: =G36 -> -14.838 | I36: =H36 -> -14.838 | J36: =I36 -> -14.838 | K36: =J36 -> -14.838 | L36: =K36 -> -14.838 | M36: =L36 -> -14.838
A37: Net cash provided by (used in) investing activities | B37: =SUM(B27:B36) -> -8488.59 | C37: =SUM(C27:C36) -> 8509.771 | D37: =SUM(D27:D36) -> 186.301 | E37: =SUM(E27:E36) -> -46.108 | F37: =SUM(F27:F36) -> -1055.465 | G37: =SUM(G27:G36) -> -318.73634 | H37: =SUM(H27:H36) -> -339.07092 | I37: =SUM(I27:I36) -> -361.03228 | ... M37: =SUM(M27:M36) -> -467.90942
A39: Cash flows from financing activities
A40: Net changes in deposits held for stablecoin holders | B40: =2176756/1000 -> 2176.756 | C40: =-20322155/1000 -> -20322.155 | D40: =19452147/1000 -> 19452.147 | E40: =17339497/1000 -> 17339.497 | F40: ='Balance Sheet'!E31-'Balance Sheet'!C31 -> 19818.221 | G40: ='Balance Sheet'!F31-'Balance Sheet'!E31 -> 5083.6467 | H40: ='Balance Sheet'!G31-'Balance Sheet'!F31 -> 5490.3385 | I40: ='Balance Sheet'!H31-'Balance Sheet'!G31 -> 5929.5655 | J40: ='Balance Sheet'!I31-'Balance Sheet'!H31 -> 6403.9308 | K40: ='Balance Sheet'!J31-'Balance Sheet'!I31 -> 6916.2452 | L40: ='Balance Sheet'!K31-'Balance Sheet'!J31 -> 7469.5448 | M40: ='Balance Sheet'!L31-'Balance Sheet'!K31 -> 8067.1084
A41: Proceeds from issuance of common stock in connection with IPO, net of underwriting discounts and commissions and offering costs | B41: 0 | C41: 0 | D41: 0 | E41: =572558/1000 -> 572.558 | F41: =E41 -> 572.558 | G41: 0 | H41: 0 | I41: 0 | J41: 0 | K41: 0 | L41: 0 | M41: 0
A42: Payment of withholding taxes on settlement of RSUs | B42: 0 | C42: 0 | D42: 0 | E42: =-121794/1000 -> -121.794 | F42: =E42*2 -> -243.588 | G42: =(F42/F17)*G17 -> -34.422292 | H42: =(G42/G17)*H17 -> -33.415804 | I42: =(H42/H17)*I17 -> -33.792216 | J42: =(I42/I17)*J17 -> -34.017111 | K42: =(J42/J17)*K17 -> -36.119694 | L42: =(K42/K17)*L17 -> -39.083655 | M42: =(L42/L17)*M17 -> -43.892096
A43: Purchase of treasury stock | B43: 0 | C43: =-8745/1000 -> -8.745 | D43: 0 | E43: 0 | F43: 0 | G43: 0 | H43: 0 | I43: 0 | J43: 0 | K43: 0 | L43: 0 | M43: 0
A44: Proceeds from issuance of preferred stock | B44: =400999/1000 -> 400.999 | C44: 0 | D44: 0 | E44: 0 | F44: 0 | G44: 0 | H44: 0 | I44: 0 | J44: 0 | K44: 0 | L44: 0 | M44: 0
A45: Capitalized transaction costs | B45: 0 | C45: 0 | D45: =-3870/1000 -> -3.87 | E45: 0 | F45: =-(F41*'Drivers & Assumptons'!$C$46) -> -33.780922 | G45: 0 | H45: 0 | I45: 0 | J45: 0 | K45: 0 | L45: 0 | M45: 0
A46: Proceeds from exercise of stock options | B46: =486/1000 -> 0.486 | C46: =1037/1000 -> 1.037 | D46: =1614/1000 -> 1.614 | E46: =6800/1000 -> 6.8 | F46: =E46*2 -> 13.6 | G46: =F46 -> 13.6 | H46: =G46 -> 13.6 | I46: =H46 -> 13.6 | J46: =I46 -> 13.6 | K46: =J46 -> 13.6 | L46: =K46 -> 13.6 | M46: =L46 -> 13.6
A47: Net cash provided by (used in) financing activities | B47: =SUM(B40:B46) -> 2578.241 | C47: =SUM(C40:C46) -> -20329.863 | D47: =SUM(D40:D46) -> 19449.891 | E47: =SUM(E40:E46) -> 17797.061 | F47: =SUM(F40:F46) -> 20127.01 | G47: =SUM(G40:G46) -> 5062.8244 | H47: =SUM(H40:H46) -> 5470.5226 | I47: =SUM(I40:I46) -> 5909.3733 | ... M47: =SUM(M40:M46) -> 8036.8163
A49: Effect of exchange rate changes on cash and cash equivalents, restricted and segregated cash | B49: =3620/1000 -> 3.62 | C49: =1097/1000 -> 1.097 | D49: =-7099/1000 -> -7.099 | E49: =53247/1000 -> 53.247 | F49: =E49 -> 53.247 | G49: =0 -> 0 | H49: =0 -> 0 | I49: =0 -> 0 | J49: =0 -> 0 | K49: =0 -> 0 | L49: =0 -> 0 | M49: =0 -> 0
A50: Unrealized gains (losses) on available-for-sale debt securities classified as cash equivalents, net of tax | B50: =136/1000 -> 0.136 | C50: =-254/1000 -> -0.254 | D50: =-224/1000 -> -0.224 | E50: 0 | F50: 0 | G50: 0 | H50: 0 | I50: 0 | J50: 0 | K50: 0 | L50: 0 | M50: 0
A51: Net increase (decrease) in cash and cash equivalents, restricted and segregated cash | B51: =B24+B37+B47+SUM(B49:B50) -> -5979.286 | C51: =C24+C37+C47+SUM(C49:C50) -> -11679.681 | D51: =D24+D37+D47+SUM(D49:D50) -> 19973.05 | E51: =E24+E37+E47+SUM(E49:E50) -> 18107.916 | F51: =F24+F37+F47+SUM(F49:F50) -> 20197.235 | G51: =G24+G37+G47+SUM(G49:G50) -> 5176.9488 | H51: =H24+H37+H47+SUM(H49:H50) -> 5531.2727 | I51: =I24+I37+I47+SUM(I49:I50) -> 5944.0817 | ... M51: =M24+M37+M47+SUM(M49:M50) -> 8084.6328
A52: Cash and cash equivalents, restricted and segregated cash at the beginning of the period | B52: =42653126/1000 -> 42653.126 | C52: =B53 -> 36673.84 | D52: =C53 -> 24994.159 | E52: =D53 -> 44967.209 | F52: =E53 -> 63075.125 | G52: =F53 -> 83272.36 | H52: =G53 -> 88449.309 | I52: =H53 -> 93980.582 | J52: =I53 -> 99924.663 | ... M52: =L53 -> 120688.16
A53: Cash and cash equivalents, restricted and segregated cash at the end of the period | B53: =B52+B51 -> 36673.84 | C53: =C52+C51 -> 24994.159 | D53: =D52+D51 -> 44967.209 | E53: =E52+E51 -> 63075.125 | F53: =F52+F51 -> 83272.36 | G53: =G52+G51 -> 88449.309 | H53: =H52+H51 -> 93980.582 | I53: =I52+I51 -> 99924.663 | ... M53: =M52+M51 -> 128772.8
Q54: =SUM(E24,E37,E47) -> 18054.669 | R54: =Q54+E49 -> 18107.916 | S54: =R54+E52 -> 63075.125
A55: Cash and cash equivalents, restricted and segregated cash consisted of: | Q55: =D47+D37+D24 -> 19980.373 | R55: =Q55+D49 -> 19973.274 | S55: =R55+D52 -> 44967.433
A56: Cash and cash equivalents | B56: =664650/1000 -> 664.65 | C56: =368623/1000 -> 368.623 | D56: =750981/1000 -> 750.981 | E56: =1118119/1000 -> 1118.119 | F56: =AVERAGE(($B$56/$B$62),($C$56/$C$62),($D$56/$D$62))*F62 -> 1375.996 | G56: =AVERAGE(($B$56/$B$62),($C$56/$C$62),($D$56/$D$62))*G62 -> 1461.5402 | H56: =AVERAGE(($B$56/$B$62),($C$56/$C$62),($D$56/$D$62))*H62 -> 1552.9391 | I56: =AVERAGE(($B$56/$B$62),($C$56/$C$62),($D$56/$D$62))*I62 -> 1651.1594 | J56: =AVERAGE(($B$56/$B$62),($C$56/$C$62),($D$56/$D$62))*J62 -> 1756.8956 | K56: =AVERAGE(($B$56/$B$62),($C$56/$C$62),($D$56/$D$62))*K62 -> 1870.9413 | L56: =AVERAGE(($B$56/$B$62),($C$56/$C$62),($D$56/$D$62))*L62 -> 1994.2564 | M56: =AVERAGE(($B$56/$B$62),($C$56/$C$62),($D$56/$D$62))*M62 -> 2127.8472
A57: Restricted cash | B57: =15914/1000 -> 15.914 | C57: =3575/1000 -> 3.575 | D57: =3558/1000 -> 3.558 | E57: =3210/1000 -> 3.21 | F57: =AVERAGE(($B$57/$B$62),($C$57/$C$62),($D$57/$D$62))*F62 -> 18.211397 | G57: =AVERAGE(($B$57/$B$62),($C$57/$C$62),($D$57/$D$62))*G62 -> 19.343579 | H57: =AVERAGE(($B$57/$B$62),($C$57/$C$62),($D$57/$D$62))*H62 -> 20.55325 | I57: =AVERAGE(($B$57/$B$62),($C$57/$C$62),($D$57/$D$62))*I62 -> 21.853202 | J57: =AVERAGE(($B$57/$B$62),($C$57/$C$62),($D$57/$D$62))*J62 -> 23.252628 | K57: =AVERAGE(($B$57/$B$62),($C$57/$C$62),($D$57/$D$62))*K62 -> 24.762029 | L57: =AVERAGE(($B$57/$B$62),($C$57/$C$62),($D$57/$D$62))*L62 -> 26.394113 | M57: =AVERAGE(($B$57/$B$62),($C$57/$C$62),($D$57/$D$62))*M62 -> 28.162196
A58: Cash and cash equivalents segregated for corporate-held stablecoins | B58: =5311/1000 -> 5.311 | C58: =275809/1000 -> 275.809 | D58: =294493/1000 -> 294.493 | E58: =588271/1000 -> 588.271 | F58: =AVERAGE(($B$58/$B$62),($C$58/$C$62),($D$58/$D$62))*F62 -> 492.1052 | G58: =AVERAGE(($B$58/$B$62),($C$58/$C$62),($D$58/$D$62))*G62 -> 522.69882 | H58: =AVERAGE(($B$58/$B$62),($C$58/$C$62),($D$58/$D$62))*H62 -> 555.38636 | I58: =AVERAGE(($B$58/$B$62),($C$58/$C$62),($D$58/$D$62))*I62 -> 590.51342 | J58: =AVERAGE(($B$58/$B$62),($C$58/$C$62),($D$58/$D$62))*J62 -> 628.32847 | K58: =AVERAGE(($B$58/$B$62),($C$58/$C$62),($D$58/$D$62))*K62 -> 669.11525 | L58: =AVERAGE(($B$58/$B$62),($C$58/$C$62),($D$58/$D$62))*L62 -> 713.21712 | M58: =AVERAGE(($B$58/$B$62),($C$58/$C$62),($D$58/$D$62))*M62 -> 760.99395
A59: Cash and cash equivalents segregated for the benefit of stablecoin holders | B59: =35987965/1000 -> 35987.965 | C59: =24346152/1000 -> 24346.152 | D59: =43918572/1000 -> 43918.572 | E59: =61365920/1000 -> 61365.92 | F59: ='Balance Sheet'!E5 -> 63820.557 | G59: ='Balance Sheet'!F5 -> 68926.201 | H59: ='Balance Sheet'!G5 -> 74440.297 | I59: ='Balance Sheet'!H5 -> 80395.521 | J59: ='Balance Sheet'!I5 -> 86827.163 | K59: ='Balance Sheet'!J5 -> 93773.336 | L59: ='Balance Sheet'!K5 -> 101275.2 | M59: ='Balance Sheet'!L5 -> 109377.22
A60: Other cash & equivalents | B60: 0 | C60: 0 | D60: 0 | E60: 0 | F60: =F62-SUM(F56:F59) -> 17565.491 | G60: =G62-SUM(G56:G59) -> 17519.525 | H60: =H62-SUM(H56:H59) -> 17411.405 | I60: =I62-SUM(I56:I59) -> 17265.616 | J60: =J62-SUM(J56:J59) -> 17087.956 | K60: =K62-SUM(K56:K59) -> 16887.242 | L60: =L62-SUM(L56:L59) -> 16679.093 | M60: =M62-SUM(M56:M59) -> 16478.574
A61: Implied Total Cash | B61: =SUM(B56:B59) -> 36673.84 | C61: =SUM(C56:C59) -> 24994.159 | D61: =SUM(D56:D59) -> 44967.604 | E61: =SUM(E56:E59) -> 63075.52 | F61: =SUM(F56:F60) -> 83272.36 | G61: =SUM(G56:G60) -> 88449.309 | H61: =SUM(H56:H60) -> 93980.582 | I61: =SUM(I56:I60) -> 99924.663 | J61: =SUM(J56:J60) -> 106323.6 | K61: =SUM(K56:K60) -> 113225.4 | L61: =SUM(L56:L60) -> 120688.16 | M61: =SUM(M56:M60) -> 128772.8
A62: Total cash and cash equivalents, restricted and segregated cash | B62: =SUM(B56:B59) -> 36673.84 | C62: =SUM(C56:C59) -> 24994.159 | D62: =SUM(D56:D59) -> 44967.604 | E62: =SUM(E56:E59) -> 63075.52 | F62: =F53 -> 83272.36 | G62: =G53 -> 88449.309 | H62: =H53 -> 93980.582 | I62: =I53 -> 99924.663 | J62: =J53 -> 106323.6 | K62: =K53 -> 113225.4 | L62: =L53 -> 120688.16 | M62: =M53 -> 128772.8
A64: Supplemental disclosure of cash flow information
A65: Cash paid for income taxes | B65: =7424/1000 -> 7.424 | C65: =81037/1000 -> 81.037 | D65: =75579/1000 -> 75.579 | E65: =13525/1000 -> 13.525
A66: Cash paid for interest | B66: =350/1000 -> 0.35 | C66: =253/1000 -> 0.253 | D66: =258/1000 -> 0.258 | E66: =180/1000 -> 0.18
A68: Supplemental schedule of non-cash activities
A69: Obligations to return digital asset collateral | B69: =-211594/1000 -> -211.594 | C69: =-7053/1000 -> -7.053 | D69: =-2700/1000 -> -2.7 | E69: 0
A70: Digital assets collateral received | B70: =-185830/1000 -> -185.83 | C70: =7053/1000 -> 7.053 | D70: =1905/1000 -> 1.905 | E70: 0
A71: Net changes in the purchase and redemption of digital financial assets | B71: 0 | C71: 0 | D71: =14328/1000 -> 14.328 | E71: =-13820/1000 -> -13.82
A72: Proceeds from sale of intangible assets | B72: 0 | C72: =21634/1000 -> 21.634 | D72: 0 | E72: 0
A73: Stablecoins repaid | B73: =-154837/1000 -> -154.837 | C73: =16459/1000 -> 16.459 | D73: =16513/1000 -> 16.513 | E73: 0
A74: Stablecoins receivable | B74: =138821/1000 -> 138.821 | C74: =-23397/1000 -> -23.397 | D74: 0 | E74: =7000/1000 -> 7
A75: Non-cash consideration for asset acquisition | B75: 0 | C75: =-209938/1000 -> -209.938 | D75: 0 | E75: 0
A76: Non-cash purchase of investments and digital assets | B76: =-20497/1000 -> -20.497 | C76: =-8937/1000 -> -8.937 | D76: =-6570/1000 -> -6.57 | E76: =-379/1000 -> -0.379
A77: Capitalized stock-based compensation expense related to internally developed software | B77: =6262/1000 -> 6.262 | C77: =13118/1000 -> 13.118 | D77: =13646/1000 -> 13.646 | E77: =68348/1000 -> 68.348
A78: Pruchase of PPE included in AP and accrued expenses | B78: 0 | C78: 0 | D78: =2874/1000 -> 2.874 | E78: =-1270/1000 -> -1.27
A79: Unrealized gain (loss) on available-for-sale debt securities | B79: =1039/1000 -> 1.039 | C79: =-815/1000 -> -0.815 | D79: =-224/1000 -> -0.224 | E79: 0
A80: Unrealized gain (loss) on convertible notes --credit risk, net of tax | B80: =-3155/1000 -> -3.155 | C80: =1182/1000 -> 1.182 | D80: =840/1000 -> 0.84 | E80: =-71/1000 -> -0.071
A81: Non-cash consideration for business combinations | B81: =-141618/1000 -> -141.618 | C81: 0 | D81: 0 | E81: =89919/1000 -> 89.919
A82: Right-of-use assets recognized on adoption of ASU 2016-02 | B82: =3273/1000 -> 3.273 | C82: 0 | D82: 0 | E82: 0
A83: Repayment of loans payable | B83: =-25000/1000 -> -25 | C83: 0 | D83: 0 | E83: 0
A84: Non-cash interest payments | B84: =-6061/1000 -> -6.061 | C84: 0 | D84: 0 | E84: 0
A85: Deferred offering costs not yet paid | B85: 0 | C85: 0 | D85: 0 | E85: =2794/1000 -> 2.794
A86: Conversion of redeemable convertible preferred stock to common stock in connection with IPO | B86: 0 | C86: 0 | D86: 0 | E86: =1140502/1000 -> 1140.502

Sheet Supporting Schedules
A1: Compensation Expense
A2: Year | B2: Headcount | C2: Avg Comp | D2: Compensation Expense | E2: Implied Cost Per Employee | F2: % Total Revenue
A3: 2022A | B3: 900 | C3: =D3/B3 -> 236623.33 | D3: =B3*C3 -> 0 | E3: =D3/B3 -> 236623.33 | F3: =D3/(_xlfn.XLOOKUP(A3,'P&L'!$B$1:$M$1,'P&L'!$B$2:$M$2)*1000000) -> 0.27583764
A4: 2023A | B4: 1200 | C4: =D4/B4 -> 246712.5 | D4: ='P&L'!C14*1000000 -> 296055000 | E4: =D4/B4 -> 246712.5 | F4: =D4/(_xlfn.XLOOKUP(A4,'P&L'!$B$1:$M$1,'P&L'!$B$2:$M$2)*1000000) -> 0.20411027
A5: 2024A | B5: 1100 | C5: =C4*(1+0.03) -> 254113.88 | D5: ='P&L'!D14*1000000 -> 2.6341e+08 | E5: =D5/B5 -> 239463.64 | F5: =D5/(_xlfn.XLOOKUP(A5,'P&L'!$B$1:$M$1,'P&L'!$B$2:$M$2)*1000000) -> 0.15714215
A6: 2025 6M Actual | B6: =B5 -> 1100 | C6: =C5*(1+0.03) -> 261737.29 | D6: ='P&L'!E14*1000000 -> 579012000 | E6: =D6/B6 -> 526374.55 | F6: =D6/(_xlfn.XLOOKUP(A6,'P&L'!$B$1:$M$1,'P&L'!$B$2:$M$2)*1000000) -> 0.46820971
A7: 2025E | B7: =B5*(1+'Drivers & Assumptons'!$C$51) -> 1188 | C7: =C6*(1+0.03) -> 269589.41 | D7: ='P&L'!F14*1000000 -> 4.7583633e+08 | E7: =D7/B7 -> 400535.63 | F7: =D7/(_xlfn.XLOOKUP(A7,'P&L'!$B$1:$M$1,'P&L'!$B$2:$M$2)*1000000) -> 0.19065
A8: 2026E | B8: =B7*(1+'Drivers & Assumptons'!$C$51) -> 1283.04 | C8: =C7*(1+0.03) -> 277677.09 | D8: ='P&L'!G14*1000000 -> 4.3115979e+08 | E8: =D8/B8 -> 336045.48 | F8: =D8/(_xlfn.XLOOKUP(A8,'P&L'!$B$1:$M$1,'P&L'!$B$2:$M$2)*1000000) -> 0.19065
A9: 2027E | B9: =B8*(1+'Drivers & Assumptons'!$C$51) -> 1385.6832 | C9: =C8*(1+0.03) -> 286007.41 | D9: ='P&L'!H14*1000000 -> 4.1855293e+08 | E9: =D9/B9 -> 302055.28 | F9: =D9/(_xlfn.XLOOKUP(A9,'P&L'!$B$1:$M$1,'P&L'!$B$2:$M$2)*1000000) -> 0.19065
A10: 2028E | B10: =B9*(1+'Drivers & Assumptons'!$C$51-0.02) -> 1468.8242 | C10: =C9*(1+0.03) -> 294587.63 | D10: ='P&L'!I14*1000000 -> 4.2326772e+08 | E10: =D10/B10 -> 288167.72 | F10: =D10/(_xlfn.XLOOKUP(A10,'P&L'!$B$1:$M$1,'P&L'!$B$2:$M$2)*1000000) -> 0.19065
A11: 2029E | B11: =B10*(1+'Drivers & Assumptons'!$C$51-0.02) -> 1556.9536 | C11: =C10*(1+0.03) -> 303425.26 | D11: ='P&L'!J14*1000000 -> 4.2608466e+08 | E11: =D11/B11 -> 273665.6 | F11: =D11/(_xlfn.XLOOKUP(A11,'P&L'!$B$1:$M$1,'P&L'!$B$2:$M$2)*1000000) -> 0.19065
A12: 2030E | B12: =B11*(1+'Drivers & Assumptons'!$C$51-0.03) -> 1634.8013 | C12: =C11*(1+0.03) -> 312528.01 | D12: ='P&L'!K14*1000000 -> 4.5242077e+08 | E12: =D12/B12 -> 276743.58 | F12: =D12/(_xlfn.XLOOKUP(A12,'P&L'!$B$1:$M$1,'P&L'!$B$2:$M$2)*1000000) -> 0.19065
A13: 2031E | B13: =B12*(1+'Drivers & Assumptons'!$C$51-0.03) -> 1716.5414 | C13: =C12*(1+0.03) -> 321903.85 | D13: ='P&L'!L14*1000000 -> 4.8954615e+08 | E13: =D13/B13 -> 285193.33 | F13: =D13/(_xlfn.XLOOKUP(A13,'P&L'!$B$1:$M$1,'P&L'!$B$2:$M$2)*1000000) -> 0.19065
A14: 2032E | B14: =B13*(1+'Drivers & Assumptons'!$C$51-0.03) -> 1802.3685 | C14: =C13*(1+0.03) -> 331560.97 | D14: ='P&L'!M14*1000000 -> 5.4977475e+08 | E14: =D14/B14 -> 305029.06 | F14: =D14/(_xlfn.XLOOKUP(A14,'P&L'!$B$1:$M$1,'P&L'!$B$2:$M$2)*1000000) -> 0.19065
A16: Capex Schedule
A17: Year | B17: Beginning PP&E | C17: Capex | D17: Depreciation | F17: Ending PP&E
A18: 2022A | B18: 0
A19: 2023A | B19: ='Balance Sheet'!B17 -> 2.619
A20: 2024A | B20: ='Balance Sheet'!C17 -> 18.682
A21: 2025 6M Actual | B21: ='Balance Sheet'!D17 -> 23.804
A22: 2025E | B22: ='Balance Sheet'!E17 -> 28.5648
A23: 2026E | B23: ='Balance Sheet'!F17 -> 29.298698
A24: 2027E | B24: ='Balance Sheet'!G17 -> 30.051451
A25: 2028E | B25: ='Balance Sheet'!H17 -> 30.823544
A26: 2029E | B26: ='Balance Sheet'!I17 -> 31.615474
A27: 2030E | B27: ='Balance Sheet'!J17 -> 32.427751
A28: 2031E | B28: ='Balance Sheet'!K17 -> 33.260897
A29: 2032E | B29: ='Balance Sheet'!L17 -> 34.115449
A33: WACC Calculation | C33: Notes
A34: Equity Value
A35: Current Share Price | B35: 134.1 | C35: 8/18/2025 close
A36: Shares Outstanding | B36: 220000000
A37: Equity Value | B37: =B35*B36 -> 29502000000
A39: Total Interest Bearing Debt | B39: 221600000
A41: Cost of Equity
A42: Risk Free Rate | B42: 0.039 | C42: Aug 2025 10-year treasury yield
A43: Beta | B43: 2 | C43: Peer Group Beta: Coinbase = 2.6, PayPal = 1.4, Block = 2.3
A44: Equity Risk Premium | B44: 0.055 | C44: U.S. Standard ERP = 5.5-6.0%
A45: Cost of Equity | B45: =B42+B43*B44 -> 0.149
A47: Cost of Debt
A48: Pre-tax | B48: 0.07 | C48: Peer bonds (e.g., Coinbase) are currently yielding around 7–8% — similar risk profile to Circle given reserve-based model, conversion risk, and regulatory exposure.
A49: After-Tax Cost of Debt | B49: =B48*(1-B58) -> 0.0553
A51: Capital Structure Weights (in millions)
A52: Equity | B52: =B37 / 1000000 -> 29502
A53: Debt | B53: =B39/1000000 -> 221.6
A54: Total Capital | B54: =SUM(B52:B53) -> 29723.6
A55: Equity Weight | B55: =B52/(B54) -> 0.99254464
A56: Debt Weight | B56: =B53/B54 -> 0.0074553553
A58: Effective Tax Rate | B58: ='Drivers & Assumptons'!C18 -> 0.21
A60: WACC | B60: =(B45*B55)+(B49*B56) -> 0.14830143

Sheet Scenarios
A1: Drivers/Outputs | B1: Base | C1: Bear | D1: Bull | E1: Flat/Stagnation
A2: Circulation Growth % | B2: ='Drivers & Assumptons'!C5 -> 0.08 | C2: 0.05 | D2: 0.15 | E2: 0.02
A3: Reserve Yield % | B3: ='Drivers & Assumptons'!C17 -> 0.041 | C3: 0.025 | D3: 0.045 | E3: 0.03
A4: Expense Growth %
A5: Adjusted EBITDA Margin % | B5: 0.2 | C5: 0.15 | D5: 0.3 | E5: 0.2
A6: Equity Beta | B6: 2 | C6: 1.8 | D6: 2.5
A7: Equity Risk Premium | B7: 0.055 | C7: 0.045 | D7: 0.065
A8: Perpetuity Growth Rate | B8: 0.025 | C8: 0.02 | D8: 0.03

Sheet Sensitivities
B2: =Valuation!K31 -> 14.214106 | C2: 0.02 | D2: 0.03 | E2: 0.04 | F2: 0.05
B3: 0.12 | C3: 14.214106 | D3: 14.214106 | E3: 14.214106 | F3: 14.214106
B4: 0.13 | C4: 14.214106 | D4: 14.214106 | E4: 14.214106 | F4: 14.214106
B5: 0.14 | C5: 14.214106 | D5: 14.214106 | E5: 14.214106 | F5: 14.214106
B6: 0.15 | C6: 14.214106 | D6: 14.214106 | E6: 14.214106 | F6: 14.214106

Sheet Valuation
A1: (in millions) | B1: 2024A | C1: 2025E | D1: 2026E | E1: 2027E | F1: 2028E | G1: 2029E | H1: 2030E | I1: 2031E | J1: 2032E | L1: Implied Terminal Value (Perp) (in millions) | M1: Implied Terminal Value (Exit Multiple Method) (in millions)
A2: Net Working Capital | B2: ='Balance Sheet'!C13-'Balance Sheet'!C34 -> -115.521 | C2: ='Balance Sheet'!E13-'Balance Sheet'!E34 -> -112.67576 | D2: ='Balance Sheet'!F13-'Balance Sheet'!F34 -> -62.77092 | E2: ='Balance Sheet'!G13-'Balance Sheet'!G34 -> -17.98804 | F2: ='Balance Sheet'!H13-'Balance Sheet'!H34 -> -18.169918 | G2: ='Balance Sheet'!I13-'Balance Sheet'!I34 -> -18.278585 | H2: ='Balance Sheet'!J13-'Balance Sheet'!J34 -> -19.294531 | I2: ='Balance Sheet'!K13-'Balance Sheet'!K34 -> -20.726687 | J2: ='Balance Sheet'!L13-'Balance Sheet'!L34 -> -23.050077 | L2: =L4*(1+'Supporting Schedules'!B60)^8 -> 29080.554 | M2: =M4*(1+'Supporting Schedules'!B60)^8 -> 48818.457
A3: Change in NWC | C3: =C2-B2 -> 2.8452365 | D3: =D2-C2 -> 49.904843 | E3: =E2-D2 -> 44.782881 | F3: =F2-E2 -> -0.18187839 | G3: =G2-F2 -> -0.10866672 | H3: =H2-G2 -> -1.0159467 | I3: =I2-H2 -> -1.4321557 | J3: =J2-I2 -> -2.3233899 | L3: Implied PV Terminal Value (Perp) (in millions) | M3: Implied PV Terminal Value (Exit Multiple Method) (in millions)
A4: UFCF | C4: ='P&L'!F43+'P&L'!F16-C3 -> 228.528 | D4: ='P&L'!G43+'P&L'!G16-D3 -> 158.9051 | E4: ='P&L'!H43+'P&L'!H16-E3 -> 157.66013 | F4: ='P&L'!I43+'P&L'!I16-F3 -> 205.00603 | G4: ='P&L'!J43+'P&L'!J16-G3 -> 206.35548 | H4: ='P&L'!K43+'P&L'!K16-H3 -> 220.56346 | I4: ='P&L'!L43+'P&L'!L16-I3 -> 239.72935 | J4: ='P&L'!M43+'P&L'!M16-J3 -> 271.03825 | L4: =(M25-(L7*1000000))/1000000 -> 9619.5647 | M4: =(M25-(M7*1000000))/1000000 -> 16148.671
A5: Implied Market UFCF Perpetuity Method | C5: =C4*$L$10 -> 2949.5501 | D5: =D4*$L$10 -> 2050.9458 | E5: =E4*$L$10 -> 2034.8774 | F5: =F4*$L$10 -> 2645.9583 | G5: =G4*$L$10 -> 2663.3752 | H5: =H4*$L$10 -> 2846.7539 | I5: =I4*$L$10 -> 3094.123 | J5: =J4*$L$10 -> 3498.2185
A6: Implied Market UFCF Exit Multiple Method | C6: =C4*$M$10 -> 1934.3965 | D6: =D4*$M$10 -> 1345.0669 | E6: =E4*$M$10 -> 1334.5288 | F6: =F4*$M$10 -> 1735.2926 | G6: =G4*$M$10 -> 1746.7151 | H6: =H4*$M$10 -> 1866.9799 | I6: =I4*$M$10 -> 2029.2114 | J6: =J4*$M$10 -> 2294.2284 | L6: Sum of Implied Market PV UFCF Perp (in millions) | M6: Sum of Implied Market PV UFCF Exit Multiple (in millions)
L7: =SUM(C9:J9) -> 18970.456 | M7: =SUM(C10:J10) -> 12441.35
A8: PV (UFCF) | C8: =C4/(1+'Supporting Schedules'!$B$60) -> 199.01395 | D8: =D4/(1+'Supporting Schedules'!$B$60) -> 138.38274 | E8: =E4/(1+'Supporting Schedules'!$B$60) -> 137.29856 | F8: =F4/(1+'Supporting Schedules'!$B$60) -> 178.52981 | G8: =G4/(1+'Supporting Schedules'!$B$60) -> 179.70497 | H8: =H4/(1+'Supporting Schedules'!$B$60) -> 192.07802 | I8: =I4/(1+'Supporting Schedules'!$B$60) -> 208.76866 | J8: =J4/(1+'Supporting Schedules'!$B$60) -> 236.03406
A9: PV (Implied Market UFCF Perpetuity Method) | C9: =C5/(1+'Supporting Schedules'!$B$60) -> 2568.62 | D9: =D5/(1+'Supporting Schedules'!$B$60) -> 1786.0692 | E9: =E5/(1+'Supporting Schedules'!$B$60) -> 1772.076 | F9: =F5/(1+'Supporting Schedules'!$B$60) -> 2304.2367 | G9: =G5/(1+'Supporting Schedules'!$B$60) -> 2319.4042 | H9: =H5/(1+'Supporting Schedules'!$B$60) -> 2479.0998 | I9: =I5/(1+'Supporting Schedules'!$B$60) -> 2694.5216 | J9: =J5/(1+'Supporting Schedules'!$B$60) -> 3046.4288 | L9: Difference from EV Market vs EV Perp | M9: Difference from EV Market vs EV Exit Multiple
A10: PV (Implied Market UFCF Exit Multiple Method) | C10: =C6/(1+'Supporting Schedules'!$B$60) -> 1684.572 | D10: =D6/(1+'Supporting Schedules'!$B$60) -> 1171.3535 | E10: =E6/(1+'Supporting Schedules'!$B$60) -> 1162.1764 | F10: =F6/(1+'Supporting Schedules'!$B$60) -> 1511.1821 | G10: =G6/(1+'Supporting Schedules'!$B$60) -> 1521.1294 | H10: =H6/(1+'Supporting Schedules'!$B$60) -> 1625.8622 | I10: =I6/(1+'Supporting Schedules'!$B$60) -> 1767.1417 | J10: =J6/(1+'Supporting Schedules'!$B$60) -> 1997.9322 | L10: =M25/(K25*1000000) -> 12.906734 | M10: =M25/(L25*1000000) -> 8.4645929
A15: Year | C15: 2025 6M Actual
A16: Convertible Debt | C16: ='Balance Sheet'!E32 -> 206.14 | K16: Terminal Value (Perpetuity + Inflation) (in millions) | L16: Terminal Value (Exit Multiple Method) (in millions)
A17: Cash & CE | C17: ='Cash Flow Statement'!E56 -> 1118.119 | K17: =J4*(1+'Drivers & Assumptons'!C48)/('Supporting Schedules'!B60-'Drivers & Assumptons'!C48) -> 2253.1304 | L17: ='P&L'!M51*'Drivers & Assumptons'!C49 -> 5767.3722
A18: Net Debt | C18: =C16-C17 -> -911.979 | K18: PV Terminal Value (in millions) | L18: PV Terminal Value (in millions)
K19: =K17/(1+'Supporting Schedules'!B60)^8 -> 745.31364 | L19: =L17/(1+'Supporting Schedules'!B60)^8 -> 1907.7907
K21: Sum of PV UFCF (in millions)
K22: =SUM(C8:J8) -> 1469.8108
K24: Enterprise Value (in millions) | L24: Enterprise Value (in millions) | M24: Enterprise Value Market
K25: =SUM(K22,K19) -> 2215.1244 | L25: =SUM(K22,L19) -> 3377.6014 | M25: =M28+(C18*1000000) -> 28590021000
K27: Equity Value (in millions) | L27: Equity Value (in millions) | M27: Equity Value Market
K28: =K25-(C18) -> 3127.1034 | L28: =L25-(C18) -> 4289.5804 | M28: ='Supporting Schedules'!B37 -> 29502000000
K30: Implied Share Price | L30: Implied Share Price | M30: Market Share Price
K31: =K28 * 1000000 /'Supporting Schedules'!$B$36 -> 14.214106 | L31: =L28 * 1000000 /'Supporting Schedules'!$B$36 -> 19.498093 | M31: =M28/'Supporting Schedules'!B36 -> 134.1
A32: Company | B32: EV ($B) | C32: EV/Revenue | D32: EV/EBITDA | E32: EV/UFCF (LTM) | F32: EV/UFCF (Forward)
A33: PayPal | B33: 71.55 | C33: 2.24 | D33: 10.03 | E33: 61 | F33: 20 | K33: EV/Revenue | L33: EV/Revenue | M33: Implied EV/Revenue
A34: Block | B34: 54 | C34: 2.8 | D34: 20 | E34: 25 | F34: 18 | K34: =K25/'P&L'!E2 -> 1.7912284 | L34: =L25/'P&L'!E2 -> 2.7312487 | M34: =M25/('P&L'!E2*1000000) -> 23.118908
A35: Coinbase | B35: 56 | C35: 11 | D35: 21 | E35: 41 | F35: 30
A36: Adyen | B36: 31 | C36: 14.4 | D36: 32 | E36: 9 | F36: 22 | K36: EV/EBITDA | L36: EV/EBITDA | M36: Implied EV/EBITDA
A37: Wise | B37: 10 | C37: 6 | D37: 21 | E37: - | F37: 28 | K37: =K25/'P&L'!$E$51 -> 8.9319532 | L37: =L25/'P&L'!$E$51 -> 13.619361 | M37: =M25/('P&L'!$E$51 * 1000000) -> 115.28234
A38: Robinhood | B38: 15 | C38: 6.5 | D38: - | E38: 40 | F38: 35
A39: CME Group | B39: 78 | C39: 12 | D39: 20 | E39: 25 | F39: 22 | K39: EV/UFCF | L39: EV/UFCF | M39: Implied EV/UFCF
K40: =K25/$J$4 -> 8.1727373 | L40: =L25/$J$4 -> 12.461715 | M40: =M25/($J$4*1000000) -> 105.48334
A41: Median | C41: =AVERAGE(C33:C39) -> 7.8485714 | D41: =AVERAGE(D39,D33:D37) -> 20.671667 | E41: =AVERAGE(E39,E38,E33:E36) -> 33.5 | F41: =AVERAGE(F33:F39) -> 25
A42: Mean | C42: =MEDIAN(C33:C39) -> 6.5 | D42: =MEDIAN(D39,D33:D37) -> 20.5 | E42: =MEDIAN(E39,E38,E33:E36) -> 32.5 | F42: =MEDIAN(F33:F39) -> 22 | M42: Implied UFCF Peer Median
M43: =(M25/F41) / 1000000 -> 1143.6008
M45: Implied UFCF Upper Peer Range
M46: =(M25/E42) / 1000000 -> 879.69295
M48: Multiple of Difference between forecasted UFCF and Implied Market UFCF
M49: =AVERAGE(M46,M43)/J4 -> 3.7324876
